{"costTC_FunctionND":
     {"1": {"1": 4, "2": 6, "3": 9}, "10": {"1": 5, "2": 1, "3": 4}, "11": {"1": 3, "2": 6, "3": 4},
      "12": {"1": 3, "2": 9, "3": 6}, "13": {"1": 5, "2": 7, "3": 2}, "14": {"1": 7, "2": 5, "3": 5},
      "15": {"1": 8, "2": 5, "3": 4}, "16": {"1": 9, "2": 5, "3": 7}, "17": {"1": 6, "2": 3, "3": 4},
      "18": {"1": 3, "2": 1, "3": 8}, "19": {"1": 5, "2": 1, "3": 3}, "2": {"1": 8, "2": 6, "3": 2},
      "20": {"1": 8, "2": 9, "3": 8}, "21": {"1": 10, "2": 5, "3": 6}, "22": {"1": 7, "2": 1, "3": 9},
      "23": {"1": 1, "2": 8, "3": 9}, "24": {"1": 2, "2": 3, "3": 6}, "25": {"1": 4, "2": 2, "3": 1},
      "26": {"1": 5, "2": 3, "3": 7}, "27": {"1": 10, "2": 10, "3": 6}, "28": {"1": 9, "2": 8, "3": 7},
      "3": {"1": 4, "2": 2, "3": 9}, "4": {"1": 2, "2": 7, "3": 7}, "5": {"1": 1, "2": 2, "3": 8},
      "6": {"1": 8, "2": 9, "3": 2}, "7": {"1": 4, "2": 3, "3": 10}, "8": {"1": 1, "2": 3, "3": 4},
      "9": {"1": 7, "2": 1, "3": 5}},
 "costWT_FunctionND":
     {"1":
          {"1": 1, "10": 1, "11": 1, "12": 1, "13": 1, "14": 1, "15": 1, "16": 1, "17": 1, "18": 1, "19": 1, "2": 1,
           "20": 1, "21": 1, "22": 1, "23": 1, "24": 1, "25": 1, "26": 1, "27": 1, "28": 1, "3": 1, "4": 1, "5": 1,
           "6": 1, "7": 1, "8": 1, "9": 1},
      "10":
          {"1": 1, "10": 1, "11": 1, "12": 1, "13": 1, "14": 1, "15": 1, "16": 1, "17": 1, "18": 1, "19": 1, "2": 1,
           "20": 1, "21": 1, "22": 1, "23": 1, "24": 1, "25": 1, "26": 1, "27": 1, "28": 1, "3": 1, "4": 1, "5": 1,
           "6": 1, "7": 1, "8": 1, "9": 1},
      "11":
          {"1": 1, "10": 1, "11": 1, "12": 1, "13": 1, "14": 1, "15": 1, "16": 1, "17": 1, "18": 1, "19": 1, "2": 1,
           "20": 1, "21": 1, "22": 1, "23": 1, "24": 1, "25": 1, "26": 1, "27": 1, "28": 1, "3": 1, "4": 1, "5": 1,
           "6": 1, "7": 1, "8": 1, "9": 1},
      "12":
          {"1": 1, "10": 1, "11": 1, "12": 1, "13": 1, "14": 1, "15": 1, "16": 1, "17": 1, "18": 1, "19": 1, "2": 1,
           "20": 1, "21": 1, "22": 1, "23": 1, "24": 1, "25": 1, "26": 1, "27": 1, "28": 1, "3": 1, "4": 1, "5": 1,
           "6": 1, "7": 1, "8": 1, "9": 1},
      "13":
          {"1": 1, "10": 1, "11": 1, "12": 1, "13": 1, "14": 1, "15": 1, "16": 1, "17": 1, "18": 1, "19": 1, "2": 1,
           "20": 1, "21": 1, "22": 1, "23": 1, "24": 1, "25": 1, "26": 1, "27": 1, "28": 1, "3": 1, "4": 1, "5": 1,
           "6": 1, "7": 1, "8": 1, "9": 1},
      "14":
          {"1": 1, "10": 1, "11": 1, "12": 1, "13": 1, "14": 1, "15": 1, "16": 1, "17": 1, "18": 1, "19": 1, "2": 1,
           "20": 1, "21": 1, "22": 1, "23": 1, "24": 1, "25": 1, "26": 1, "27": 1, "28": 1, "3": 1, "4": 1, "5": 1,
           "6": 1, "7": 1, "8": 1, "9": 1},
      "15":
          {"1": 1, "10": 1, "11": 1, "12": 1, "13": 1, "14": 1, "15": 1, "16": 1, "17": 1, "18": 1, "19": 1, "2": 1,
           "20": 1, "21": 1, "22": 1, "23": 1, "24": 1, "25": 1, "26": 1, "27": 1, "28": 1, "3": 1, "4": 1, "5": 1,
           "6": 1, "7": 1, "8": 1, "9": 1},
      "16":
          {"1": 1, "10": 1, "11": 1, "12": 1, "13": 1, "14": 1, "15": 1, "16": 1, "17": 1, "18": 1, "19": 1, "2": 1,
           "20": 1, "21": 1, "22": 1, "23": 1, "24": 1, "25": 1, "26": 1, "27": 1, "28": 1, "3": 1, "4": 1, "5": 1,
           "6": 1, "7": 1, "8": 1, "9": 1},
      "17":
          {"1": 1, "10": 1, "11": 1, "12": 1, "13": 1, "14": 1, "15": 1, "16": 1, "17": 1, "18": 1, "19": 1, "2": 1,
           "20": 1, "21": 1, "22": 1, "23": 1, "24": 1, "25": 1, "26": 1, "27": 1, "28": 1, "3": 1, "4": 1, "5": 1,
           "6": 1, "7": 1, "8": 1, "9": 1},
      "18":
          {"1": 1, "10": 1, "11": 1, "12": 1, "13": 1, "14": 1, "15": 1, "16": 1, "17": 1, "18": 1, "19": 1, "2": 1,
           "20": 1, "21": 1, "22": 1, "23": 1, "24": 1, "25": 1, "26": 1, "27": 1, "28": 1, "3": 1, "4": 1, "5": 1,
           "6": 1, "7": 1, "8": 1, "9": 1},
      "19":
          {"1": 1, "10": 1, "11": 1, "12": 1, "13": 1, "14": 1, "15": 1, "16": 1, "17": 1, "18": 1, "19": 1, "2": 1,
           "20": 1, "21": 1, "22": 1, "23": 1, "24": 1, "25": 1, "26": 1, "27": 1, "28": 1, "3": 1, "4": 1, "5": 1,
           "6": 1, "7": 1, "8": 1, "9": 1},
      "2":
          {"1": 1, "10": 1, "11": 1, "12": 1, "13": 1, "14": 1, "15": 1, "16": 1, "17": 1, "18": 1, "19": 1, "2": 1,
           "20": 1, "21": 1, "22": 1, "23": 1, "24": 1, "25": 1, "26": 1, "27": 1, "28": 1, "3": 1, "4": 1, "5": 1,
           "6": 1, "7": 1, "8": 1, "9": 1},
      "20":
          {"1": 1, "10": 1, "11": 1, "12": 1, "13": 1, "14": 1, "15": 1, "16": 1, "17": 1, "18": 1, "19": 1, "2": 1,
           "20": 1, "21": 1, "22": 1, "23": 1, "24": 1, "25": 1, "26": 1, "27": 1, "28": 1, "3": 1, "4": 1, "5": 1,
           "6": 1, "7": 1, "8": 1, "9": 1},
      "21":
          {"1": 1, "10": 1, "11": 1, "12": 1, "13": 1, "14": 1, "15": 1, "16": 1, "17": 1, "18": 1, "19": 1, "2": 1,
           "20": 1, "21": 1, "22": 1, "23": 1, "24": 1, "25": 1, "26": 1, "27": 1, "28": 1, "3": 1, "4": 1, "5": 1,
           "6": 1, "7": 1, "8": 1, "9": 1},
      "22":
          {"1": 1, "10": 1, "11": 1, "12": 1, "13": 1, "14": 1, "15": 1, "16": 1, "17": 1, "18": 1, "19": 1, "2": 1,
           "20": 1, "21": 1, "22": 1, "23": 1, "24": 1, "25": 1, "26": 1, "27": 1, "28": 1, "3": 1, "4": 1, "5": 1,
           "6": 1, "7": 1, "8": 1, "9": 1},
      "23":
          {"1": 1, "10": 1, "11": 1, "12": 1, "13": 1, "14": 1, "15": 1, "16": 1, "17": 1, "18": 1, "19": 1, "2": 1,
           "20": 1, "21": 1, "22": 1, "23": 1, "24": 1, "25": 1, "26": 1, "27": 1, "28": 1, "3": 1, "4": 1, "5": 1,
           "6": 1, "7": 1, "8": 1, "9": 1},
      "24":
          {"1": 1, "10": 1, "11": 1, "12": 1, "13": 1, "14": 1, "15": 1, "16": 1, "17": 1, "18": 1, "19": 1, "2": 1,
           "20": 1, "21": 1, "22": 1, "23": 1, "24": 1, "25": 1, "26": 1, "27": 1, "28": 1, "3": 1, "4": 1, "5": 1,
           "6": 1, "7": 1, "8": 1, "9": 1},
      "25":
          {"1": 1, "10": 1, "11": 1, "12": 1, "13": 1, "14": 1, "15": 1, "16": 1, "17": 1, "18": 1, "19": 1, "2": 1,
           "20": 1, "21": 1, "22": 1, "23": 1, "24": 1, "25": 1, "26": 1, "27": 1, "28": 1, "3": 1, "4": 1, "5": 1,
           "6": 1, "7": 1, "8": 1, "9": 1},
      "26":
          {"1": 1, "10": 1, "11": 1, "12": 1, "13": 1, "14": 1, "15": 1, "16": 1, "17": 1, "18": 1, "19": 1, "2": 1,
           "20": 1, "21": 1, "22": 1, "23": 1, "24": 1, "25": 1, "26": 1, "27": 1, "28": 1, "3": 1, "4": 1, "5": 1,
           "6": 1, "7": 1, "8": 1, "9": 1},
      "27":
          {"1": 1, "10": 1, "11": 1, "12": 1, "13": 1, "14": 1, "15": 1, "16": 1, "17": 1, "18": 1, "19": 1, "2": 1,
           "20": 1, "21": 1, "22": 1, "23": 1, "24": 1, "25": 1, "26": 1, "27": 1, "28": 1, "3": 1, "4": 1, "5": 1,
           "6": 1, "7": 1, "8": 1, "9": 1},
      "28":
          {"1": 1, "10": 1, "11": 1, "12": 1, "13": 1, "14": 1, "15": 1, "16": 1, "17": 1, "18": 1, "19": 1, "2": 1,
           "20": 1, "21": 1, "22": 1, "23": 1, "24": 1, "25": 1, "26": 1, "27": 1, "28": 1, "3": 1, "4": 1, "5": 1,
           "6": 1, "7": 1, "8": 1, "9": 1},
      "29":
          {"1": 1, "10": 1, "11": 1, "12": 1, "13": 1, "14": 1, "15": 1, "16": 1, "17": 1, "18": 1, "19": 1, "2": 1,
           "20": 1, "21": 1, "22": 1, "23": 1, "24": 1, "25": 1, "26": 1, "27": 1, "28": 1, "3": 1, "4": 1, "5": 1,
           "6": 1, "7": 1, "8": 1, "9": 1},
      "3":
          {"1": 1, "10": 1, "11": 1, "12": 1, "13": 1, "14": 1, "15": 1, "16": 1, "17": 1, "18": 1, "19": 1, "2": 1,
           "20": 1, "21": 1, "22": 1, "23": 1, "24": 1, "25": 1, "26": 1, "27": 1, "28": 1, "3": 1, "4": 1, "5": 1,
           "6": 1, "7": 1, "8": 1, "9": 1},
      "4":
          {"1": 1, "10": 1, "11": 1, "12": 1, "13": 1, "14": 1, "15": 1, "16": 1, "17": 1, "18": 1, "19": 1, "2": 1,
           "20": 1, "21": 1, "22": 1, "23": 1, "24": 1, "25": 1, "26": 1, "27": 1, "28": 1, "3": 1, "4": 1, "5": 1,
           "6": 1, "7": 1, "8": 1, "9": 1},
      "5":
          {"1": 1, "10": 1, "11": 1, "12": 1, "13": 1, "14": 1, "15": 1, "16": 1, "17": 1, "18": 1, "19": 1, "2": 1,
           "20": 1, "21": 1, "22": 1, "23": 1, "24": 1, "25": 1, "26": 1, "27": 1, "28": 1, "3": 1, "4": 1, "5": 1,
           "6": 1, "7": 1, "8": 1, "9": 1},
      "6":
          {"1": 1, "10": 1, "11": 1, "12": 1, "13": 1, "14": 1, "15": 1, "16": 1, "17": 1, "18": 1, "19": 1, "2": 1,
           "20": 1, "21": 1, "22": 1, "23": 1, "24": 1, "25": 1, "26": 1, "27": 1, "28": 1, "3": 1, "4": 1, "5": 1,
           "6": 1, "7": 1, "8": 1, "9": 1},
      "7":
          {"1": 1, "10": 1, "11": 1, "12": 1, "13": 1, "14": 1, "15": 1, "16": 1, "17": 1, "18": 1, "19": 1, "2": 1,
           "20": 1, "21": 1, "22": 1, "23": 1, "24": 1, "25": 1, "26": 1, "27": 1, "28": 1, "3": 1, "4": 1, "5": 1,
           "6": 1, "7": 1, "8": 1, "9": 1},
      "8":
          {"1": 1, "10": 1, "11": 1, "12": 1, "13": 1, "14": 1, "15": 1, "16": 1, "17": 1, "18": 1, "19": 1, "2": 1,
           "20": 1, "21": 1, "22": 1, "23": 1, "24": 1, "25": 1, "26": 1, "27": 1, "28": 1, "3": 1, "4": 1, "5": 1,
           "6": 1, "7": 1, "8": 1, "9": 1},
      "9":
          {"1": 1, "10": 1, "11": 1, "12": 1, "13": 1, "14": 1, "15": 1, "16": 1, "17": 1, "18": 1, "19": 1, "2": 1,
           "20": 1, "21": 1, "22": 1, "23": 1, "24": 1, "25": 1, "26": 1, "27": 1, "28": 1, "3": 1, "4": 1, "5": 1,
           "6": 1, "7": 1, "8": 1, "9": 1}},
 "demand_Function1D": {"1": 31, "2": 32, "3": 31}, "fin1": 812, "fin2": 1, "fin3": 84, "fin4": 10, "fin5": 29,
 "fin6": 50, "fin7": 3, "fin8": 32, "maxCost": 35, "n_customer": 3, "n_transshipment": 28, "n_warehouses": 29,
 "stock_Function1D":
     {"1": 36, "10": 37, "11": 49, "12": 39, "13": 44, "14": 48, "15": 37, "16": 43, "17": 41, "18": 34, "19": 32,
      "2": 50, "20": 33, "21": 39, "22": 45, "23": 49, "24": 43, "25": 47, "26": 34, "27": 37, "28": 46, "29": 40,
      "3": 34, "4": 37, "5": 36, "6": 39, "7": 35, "8": 45, "9": 45}}