{"class_Function1D":
     {"1": 5, "10": 1, "11": 8, "12": 7, "13": 9, "14": 9, "15": 2, "16": 3, "17": 3, "18": 4, "19": 8, "2": 6,
      "20": 10, "21": 8, "22": 5, "23": 3, "24": 8, "25": 3, "26": 4, "27": 7, "3": 3, "4": 3, "5": 6, "6": 8, "7": 4,
      "8": 10, "9": 10},
 "deck_length": 91, "deck_width": 44, "fin1": 27, "fin2": 27, "fin3": 27, "fin4": 2, "fin5": 66,
 "length_Function1D":
     {"1": 1, "10": 1, "11": 1, "12": 1, "13": 21, "14": 1, "15": 1, "16": 6, "17": 1, "18": 8, "19": 13, "2": 1,
      "20": 1, "21": 1, "22": 1, "23": 1, "24": 1, "25": 1, "26": 25, "27": 1, "3": 1, "4": 1, "5": 5, "6": 16, "7": 1,
      "8": 1, "9": 1},
 "n_classes": 10, "n_containers": 27,
 "separation_FunctionAsRelationR3_RelationAsSetR3_ExplicitR3_1_Explicit":
     {"1": {"1": 1, "2": 5}, "2": {"1": 2, "2": 4}},
 "separation_FunctionAsRelationR3_RelationAsSetR3_ExplicitR3_2": {"1": 35, "2": 66},
 "width_Function1D":
     {"1": 1, "10": 1, "11": 1, "12": 1, "13": 26, "14": 1, "15": 1, "16": 11, "17": 1, "18": 1, "19": 30, "2": 1,
      "20": 1, "21": 1, "22": 1, "23": 1, "24": 1, "25": 1, "26": 1, "27": 1, "3": 1, "4": 1, "5": 10, "6": 36, "7": 1,
      "8": 1, "9": 1}}