{"class_Function1D":
     {"1": 10, "10": 10, "11": 1, "12": 7, "13": 9, "14": 4, "15": 8, "16": 9, "17": 2, "18": 7, "19": 10, "2": 10,
      "20": 10, "21": 9, "22": 9, "23": 8, "24": 3, "25": 2, "26": 6, "27": 5, "28": 5, "3": 8, "4": 5, "5": 3, "6": 7,
      "7": 1, "8": 6, "9": 4},
 "deck_length": 45, "deck_width": 88, "fin1": 28, "fin2": 28, "fin3": 28, "fin4": 0, "fin5": 0,
 "length_Function1D":
     {"1": 31, "10": 36, "11": 41, "12": 12, "13": 23, "14": 12, "15": 18, "16": 31, "17": 2, "18": 11, "19": 26,
      "2": 42, "20": 6, "21": 36, "22": 16, "23": 41, "24": 4, "25": 1, "26": 38, "27": 45, "28": 45, "3": 21, "4": 18,
      "5": 13, "6": 5, "7": 31, "8": 17, "9": 42},
 "n_classes": 10, "n_containers": 28, "separation_FunctionAsRelationR3_RelationAsSetR3_ExplicitR3_1_Explicit": {},
 "separation_FunctionAsRelationR3_RelationAsSetR3_ExplicitR3_2": {},
 "width_Function1D":
     {"1": 1, "10": 1, "11": 1, "12": 1, "13": 1, "14": 1, "15": 1, "16": 1, "17": 1, "18": 1, "19": 2, "2": 1, "20": 1,
      "21": 3, "22": 1, "23": 1, "24": 1, "25": 1, "26": 1, "27": 1, "28": 71, "3": 1, "4": 1, "5": 1, "6": 2, "7": 1,
      "8": 1, "9": 1}}