{"blksize_delta_Function1D":
     {"1": 7, "10": 7, "11": 7, "12": 7, "13": 7, "14": 7, "15": 7, "16": 7, "2": 7, "3": 7, "4": 7, "5": 7, "6": 7,
      "7": 7, "8": 7, "9": 7},
 "fin1": 48, "fin2": 5, "fin3": 16, "fin4": 10, "fin5": 16, "fin6": 7, "fin7": 86,
 "maxcars_Function1D":
     {"1": 10, "10": 10, "11": 10, "12": 10, "13": 10, "14": 10, "15": 10, "16": 10, "2": 10, "3": 10, "4": 10, "5": 10,
      "6": 10, "7": 10, "8": 10, "9": 10},
 "n_cars": 240, "n_classes": 48, "n_options": 16,
 "quantity_Function1D":
     {"1": 5, "10": 5, "11": 5, "12": 5, "13": 5, "14": 5, "15": 5, "16": 5, "17": 5, "18": 5, "19": 5, "2": 5, "20": 5,
      "21": 5, "22": 5, "23": 5, "24": 5, "25": 5, "26": 5, "27": 5, "28": 5, "29": 5, "3": 5, "30": 5, "31": 5,
      "32": 5, "33": 5, "34": 5, "35": 5, "36": 5, "37": 5, "38": 5, "39": 5, "4": 5, "40": 5, "41": 5, "42": 5,
      "43": 5, "44": 5, "45": 5, "46": 5, "47": 5, "48": 5, "5": 5, "6": 5, "7": 5, "8": 5, "9": 5},
 "usage_RelationAsSet_Explicit_1":
     {"1": 1, "10": 6, "11": 7, "12": 8, "13": 8, "14": 9, "15": 10, "16": 10, "17": 10, "18": 11, "19": 12, "2": 2,
      "20": 13, "21": 13, "22": 14, "23": 15, "24": 15, "25": 15, "26": 16, "27": 16, "28": 16, "29": 17, "3": 2,
      "30": 18, "31": 19, "32": 20, "33": 20, "34": 20, "35": 21, "36": 21, "37": 21, "38": 21, "39": 22, "4": 2,
      "40": 22, "41": 23, "42": 24, "43": 25, "44": 25, "45": 26, "46": 26, "47": 26, "48": 27, "49": 28, "5": 3,
      "50": 28, "51": 29, "52": 30, "53": 30, "54": 30, "55": 30, "56": 31, "57": 32, "58": 33, "59": 33, "6": 4,
      "60": 33, "61": 34, "62": 35, "63": 35, "64": 35, "65": 35, "66": 36, "67": 36, "68": 36, "69": 37, "7": 5,
      "70": 38, "71": 39, "72": 39, "73": 40, "74": 40, "75": 41, "76": 42, "77": 43, "78": 44, "79": 44, "8": 6,
      "80": 44, "81": 45, "82": 45, "83": 45, "84": 46, "85": 47, "86": 48, "9": 6},
 "usage_RelationAsSet_Explicit_2":
     {"1": 14, "10": 16, "11": 16, "12": 7, "13": 11, "14": 16, "15": 4, "16": 9, "17": 14, "18": 16, "19": 16, "2": 6,
      "20": 5, "21": 7, "22": 2, "23": 2, "24": 7, "25": 10, "26": 5, "27": 6, "28": 14, "29": 14, "3": 12, "30": 11,
      "31": 1, "32": 2, "33": 3, "34": 10, "35": 6, "36": 9, "37": 11, "38": 14, "39": 4, "4": 13, "40": 6, "41": 16,
      "42": 12, "43": 3, "44": 15, "45": 2, "46": 6, "47": 8, "48": 8, "49": 1, "5": 16, "50": 8, "51": 9, "52": 8,
      "53": 11, "54": 12, "55": 14, "56": 16, "57": 4, "58": 3, "59": 7, "6": 16, "60": 13, "61": 11, "62": 5, "63": 8,
      "64": 11, "65": 15, "66": 7, "67": 11, "68": 15, "69": 1, "7": 5, "70": 15, "71": 6, "72": 15, "73": 5, "74": 14,
      "75": 1, "76": 2, "77": 2, "78": 6, "79": 9, "8": 2, "80": 14, "81": 8, "82": 10, "83": 16, "84": 2, "85": 16,
      "86": 3, "9": 14}}