{"costTC_FunctionND":
     {"1": {"1": 1, "10": 1, "11": 1, "2": 1, "3": 1, "4": 1, "5": 1, "6": 1, "7": 1, "8": 1, "9": 1},
      "10": {"1": 1, "10": 1, "11": 1, "2": 1, "3": 1, "4": 1, "5": 1, "6": 1, "7": 1, "8": 1, "9": 1},
      "11": {"1": 1, "10": 1, "11": 1, "2": 1, "3": 1, "4": 1, "5": 1, "6": 1, "7": 1, "8": 1, "9": 1},
      "12": {"1": 1, "10": 1, "11": 1, "2": 1, "3": 1, "4": 1, "5": 1, "6": 1, "7": 1, "8": 1, "9": 1},
      "13": {"1": 1, "10": 1, "11": 1, "2": 1, "3": 1, "4": 1, "5": 1, "6": 1, "7": 1, "8": 1, "9": 1},
      "14": {"1": 1, "10": 1, "11": 1, "2": 1, "3": 1, "4": 1, "5": 1, "6": 1, "7": 1, "8": 1, "9": 1},
      "15": {"1": 1, "10": 1, "11": 1, "2": 1, "3": 1, "4": 1, "5": 1, "6": 1, "7": 1, "8": 1, "9": 1},
      "16": {"1": 1, "10": 1, "11": 1, "2": 1, "3": 1, "4": 1, "5": 1, "6": 1, "7": 1, "8": 1, "9": 1},
      "17": {"1": 1, "10": 1, "11": 1, "2": 1, "3": 1, "4": 1, "5": 1, "6": 1, "7": 1, "8": 1, "9": 1},
      "18": {"1": 1, "10": 1, "11": 1, "2": 1, "3": 1, "4": 1, "5": 1, "6": 1, "7": 1, "8": 1, "9": 1},
      "19": {"1": 1, "10": 1, "11": 1, "2": 1, "3": 1, "4": 1, "5": 1, "6": 1, "7": 1, "8": 1, "9": 1},
      "2": {"1": 1, "10": 1, "11": 1, "2": 1, "3": 1, "4": 1, "5": 1, "6": 1, "7": 1, "8": 1, "9": 1},
      "20": {"1": 1, "10": 1, "11": 1, "2": 1, "3": 1, "4": 1, "5": 1, "6": 1, "7": 1, "8": 1, "9": 1},
      "21": {"1": 1, "10": 1, "11": 1, "2": 1, "3": 1, "4": 1, "5": 1, "6": 1, "7": 1, "8": 1, "9": 1},
      "22": {"1": 1, "10": 1, "11": 1, "2": 1, "3": 1, "4": 1, "5": 1, "6": 1, "7": 1, "8": 1, "9": 1},
      "23": {"1": 1, "10": 1, "11": 1, "2": 1, "3": 1, "4": 1, "5": 1, "6": 1, "7": 1, "8": 1, "9": 1},
      "24": {"1": 1, "10": 1, "11": 1, "2": 1, "3": 1, "4": 1, "5": 1, "6": 1, "7": 1, "8": 1, "9": 1},
      "25": {"1": 1, "10": 1, "11": 1, "2": 1, "3": 1, "4": 1, "5": 1, "6": 1, "7": 1, "8": 1, "9": 1},
      "26": {"1": 1, "10": 1, "11": 1, "2": 1, "3": 1, "4": 1, "5": 1, "6": 1, "7": 1, "8": 1, "9": 1},
      "27": {"1": 1, "10": 1, "11": 1, "2": 1, "3": 1, "4": 1, "5": 1, "6": 1, "7": 1, "8": 1, "9": 1},
      "28": {"1": 1, "10": 1, "11": 1, "2": 1, "3": 1, "4": 1, "5": 1, "6": 1, "7": 1, "8": 1, "9": 1},
      "29": {"1": 1, "10": 1, "11": 1, "2": 1, "3": 1, "4": 1, "5": 1, "6": 1, "7": 1, "8": 1, "9": 1},
      "3": {"1": 1, "10": 1, "11": 1, "2": 1, "3": 1, "4": 1, "5": 1, "6": 1, "7": 1, "8": 1, "9": 1},
      "30": {"1": 1, "10": 1, "11": 1, "2": 1, "3": 1, "4": 1, "5": 1, "6": 1, "7": 1, "8": 1, "9": 1},
      "31": {"1": 1, "10": 1, "11": 1, "2": 1, "3": 1, "4": 1, "5": 1, "6": 1, "7": 1, "8": 1, "9": 1},
      "32": {"1": 1, "10": 1, "11": 1, "2": 1, "3": 1, "4": 1, "5": 1, "6": 1, "7": 1, "8": 1, "9": 1},
      "33": {"1": 1, "10": 1, "11": 1, "2": 1, "3": 1, "4": 1, "5": 1, "6": 1, "7": 1, "8": 1, "9": 1},
      "34": {"1": 1, "10": 1, "11": 1, "2": 1, "3": 1, "4": 1, "5": 1, "6": 1, "7": 1, "8": 1, "9": 1},
      "35": {"1": 1, "10": 1, "11": 1, "2": 1, "3": 1, "4": 1, "5": 1, "6": 1, "7": 1, "8": 1, "9": 1},
      "36": {"1": 1, "10": 1, "11": 1, "2": 1, "3": 1, "4": 1, "5": 1, "6": 1, "7": 1, "8": 1, "9": 1},
      "4": {"1": 1, "10": 1, "11": 1, "2": 1, "3": 1, "4": 1, "5": 1, "6": 1, "7": 1, "8": 1, "9": 1},
      "5": {"1": 1, "10": 1, "11": 1, "2": 1, "3": 1, "4": 1, "5": 1, "6": 1, "7": 1, "8": 1, "9": 1},
      "6": {"1": 1, "10": 1, "11": 1, "2": 1, "3": 1, "4": 1, "5": 1, "6": 1, "7": 1, "8": 1, "9": 1},
      "7": {"1": 1, "10": 1, "11": 1, "2": 1, "3": 1, "4": 1, "5": 1, "6": 1, "7": 1, "8": 1, "9": 1},
      "8": {"1": 1, "10": 1, "11": 1, "2": 1, "3": 1, "4": 1, "5": 1, "6": 1, "7": 1, "8": 1, "9": 1},
      "9": {"1": 1, "10": 1, "11": 1, "2": 1, "3": 1, "4": 1, "5": 1, "6": 1, "7": 1, "8": 1, "9": 1}},
 "costWT_FunctionND":
     {"1":
          {"1": 1, "10": 2, "11": 1, "12": 1, "13": 2, "14": 2, "15": 2, "16": 1, "17": 1, "18": 2, "19": 1, "2": 2,
           "20": 2, "21": 2, "22": 1, "23": 2, "24": 1, "25": 1, "26": 1, "27": 1, "28": 1, "29": 1, "3": 1, "30": 1,
           "31": 1, "32": 2, "33": 1, "34": 1, "35": 2, "36": 2, "4": 1, "5": 1, "6": 1, "7": 2, "8": 2, "9": 2},
      "10":
          {"1": 1, "10": 2, "11": 2, "12": 2, "13": 1, "14": 1, "15": 2, "16": 1, "17": 1, "18": 2, "19": 2, "2": 1,
           "20": 2, "21": 1, "22": 2, "23": 2, "24": 2, "25": 1, "26": 1, "27": 1, "28": 2, "29": 2, "3": 2, "30": 1,
           "31": 2, "32": 1, "33": 2, "34": 2, "35": 2, "36": 1, "4": 2, "5": 1, "6": 1, "7": 2, "8": 1, "9": 1},
      "11":
          {"1": 2, "10": 2, "11": 1, "12": 2, "13": 1, "14": 2, "15": 2, "16": 2, "17": 1, "18": 2, "19": 1, "2": 1,
           "20": 2, "21": 2, "22": 2, "23": 2, "24": 1, "25": 2, "26": 2, "27": 2, "28": 1, "29": 1, "3": 2, "30": 2,
           "31": 2, "32": 2, "33": 1, "34": 1, "35": 2, "36": 2, "4": 2, "5": 1, "6": 2, "7": 1, "8": 2, "9": 1},
      "12":
          {"1": 2, "10": 1, "11": 2, "12": 1, "13": 1, "14": 1, "15": 2, "16": 1, "17": 1, "18": 2, "19": 2, "2": 2,
           "20": 1, "21": 1, "22": 2, "23": 2, "24": 2, "25": 2, "26": 1, "27": 1, "28": 2, "29": 1, "3": 1, "30": 1,
           "31": 2, "32": 2, "33": 2, "34": 1, "35": 2, "36": 2, "4": 2, "5": 2, "6": 1, "7": 1, "8": 1, "9": 1},
      "13":
          {"1": 2, "10": 2, "11": 1, "12": 2, "13": 1, "14": 1, "15": 2, "16": 1, "17": 2, "18": 2, "19": 1, "2": 1,
           "20": 2, "21": 2, "22": 1, "23": 2, "24": 1, "25": 1, "26": 2, "27": 2, "28": 2, "29": 2, "3": 1, "30": 1,
           "31": 1, "32": 2, "33": 2, "34": 1, "35": 2, "36": 1, "4": 2, "5": 2, "6": 2, "7": 2, "8": 1, "9": 2},
      "14":
          {"1": 1, "10": 1, "11": 1, "12": 2, "13": 2, "14": 2, "15": 2, "16": 1, "17": 2, "18": 1, "19": 1, "2": 1,
           "20": 2, "21": 2, "22": 1, "23": 1, "24": 2, "25": 2, "26": 1, "27": 2, "28": 1, "29": 2, "3": 1, "30": 2,
           "31": 1, "32": 1, "33": 1, "34": 2, "35": 2, "36": 1, "4": 2, "5": 2, "6": 1, "7": 2, "8": 2, "9": 1},
      "15":
          {"1": 2, "10": 1, "11": 1, "12": 2, "13": 2, "14": 1, "15": 2, "16": 1, "17": 1, "18": 2, "19": 1, "2": 2,
           "20": 1, "21": 1, "22": 1, "23": 1, "24": 1, "25": 2, "26": 2, "27": 1, "28": 2, "29": 2, "3": 1, "30": 1,
           "31": 2, "32": 2, "33": 2, "34": 2, "35": 2, "36": 1, "4": 1, "5": 1, "6": 1, "7": 1, "8": 2, "9": 1},
      "16":
          {"1": 1, "10": 2, "11": 1, "12": 2, "13": 1, "14": 2, "15": 2, "16": 1, "17": 1, "18": 1, "19": 1, "2": 2,
           "20": 2, "21": 2, "22": 2, "23": 2, "24": 1, "25": 2, "26": 1, "27": 1, "28": 2, "29": 2, "3": 2, "30": 1,
           "31": 1, "32": 1, "33": 1, "34": 1, "35": 1, "36": 1, "4": 2, "5": 2, "6": 2, "7": 2, "8": 1, "9": 2},
      "17":
          {"1": 2, "10": 2, "11": 1, "12": 1, "13": 2, "14": 2, "15": 1, "16": 1, "17": 2, "18": 1, "19": 2, "2": 1,
           "20": 1, "21": 1, "22": 2, "23": 1, "24": 2, "25": 1, "26": 2, "27": 1, "28": 2, "29": 2, "3": 2, "30": 2,
           "31": 1, "32": 2, "33": 1, "34": 1, "35": 2, "36": 1, "4": 1, "5": 1, "6": 2, "7": 2, "8": 1, "9": 2},
      "18":
          {"1": 2, "10": 1, "11": 2, "12": 1, "13": 2, "14": 2, "15": 1, "16": 1, "17": 1, "18": 1, "19": 1, "2": 1,
           "20": 2, "21": 2, "22": 1, "23": 1, "24": 1, "25": 2, "26": 2, "27": 1, "28": 2, "29": 2, "3": 2, "30": 2,
           "31": 2, "32": 1, "33": 2, "34": 2, "35": 2, "36": 1, "4": 1, "5": 1, "6": 1, "7": 1, "8": 1, "9": 2},
      "19":
          {"1": 2, "10": 1, "11": 2, "12": 2, "13": 2, "14": 1, "15": 1, "16": 1, "17": 1, "18": 1, "19": 1, "2": 2,
           "20": 2, "21": 1, "22": 2, "23": 2, "24": 1, "25": 1, "26": 2, "27": 2, "28": 2, "29": 2, "3": 1, "30": 2,
           "31": 2, "32": 2, "33": 1, "34": 1, "35": 2, "36": 2, "4": 2, "5": 2, "6": 1, "7": 1, "8": 2, "9": 2},
      "2":
          {"1": 1, "10": 2, "11": 2, "12": 2, "13": 2, "14": 2, "15": 1, "16": 2, "17": 1, "18": 2, "19": 2, "2": 1,
           "20": 2, "21": 2, "22": 2, "23": 1, "24": 1, "25": 2, "26": 2, "27": 1, "28": 2, "29": 2, "3": 2, "30": 1,
           "31": 1, "32": 2, "33": 1, "34": 2, "35": 2, "36": 2, "4": 1, "5": 1, "6": 2, "7": 1, "8": 1, "9": 1},
      "20":
          {"1": 2, "10": 2, "11": 1, "12": 1, "13": 2, "14": 1, "15": 1, "16": 1, "17": 1, "18": 1, "19": 1, "2": 1,
           "20": 1, "21": 1, "22": 2, "23": 1, "24": 1, "25": 2, "26": 1, "27": 2, "28": 2, "29": 2, "3": 1, "30": 1,
           "31": 1, "32": 1, "33": 2, "34": 2, "35": 1, "36": 2, "4": 2, "5": 2, "6": 1, "7": 1, "8": 2, "9": 2},
      "21":
          {"1": 2, "10": 2, "11": 1, "12": 1, "13": 2, "14": 2, "15": 1, "16": 2, "17": 2, "18": 1, "19": 1, "2": 2,
           "20": 1, "21": 2, "22": 2, "23": 2, "24": 2, "25": 1, "26": 1, "27": 2, "28": 1, "29": 1, "3": 2, "30": 2,
           "31": 1, "32": 2, "33": 1, "34": 1, "35": 2, "36": 1, "4": 2, "5": 1, "6": 2, "7": 1, "8": 2, "9": 2},
      "22":
          {"1": 2, "10": 1, "11": 2, "12": 2, "13": 2, "14": 1, "15": 2, "16": 2, "17": 1, "18": 2, "19": 2, "2": 2,
           "20": 1, "21": 2, "22": 1, "23": 1, "24": 1, "25": 1, "26": 1, "27": 1, "28": 2, "29": 2, "3": 2, "30": 1,
           "31": 1, "32": 1, "33": 1, "34": 2, "35": 2, "36": 2, "4": 2, "5": 2, "6": 2, "7": 2, "8": 1, "9": 1},
      "23":
          {"1": 2, "10": 2, "11": 1, "12": 1, "13": 1, "14": 2, "15": 1, "16": 2, "17": 2, "18": 1, "19": 1, "2": 1,
           "20": 1, "21": 2, "22": 1, "23": 1, "24": 2, "25": 1, "26": 1, "27": 1, "28": 2, "29": 2, "3": 1, "30": 1,
           "31": 2, "32": 1, "33": 1, "34": 1, "35": 1, "36": 1, "4": 2, "5": 2, "6": 2, "7": 1, "8": 1, "9": 2},
      "24":
          {"1": 2, "10": 1, "11": 1, "12": 1, "13": 2, "14": 1, "15": 2, "16": 2, "17": 2, "18": 2, "19": 2, "2": 2,
           "20": 1, "21": 2, "22": 2, "23": 1, "24": 1, "25": 2, "26": 2, "27": 2, "28": 2, "29": 2, "3": 2, "30": 2,
           "31": 1, "32": 1, "33": 2, "34": 1, "35": 2, "36": 1, "4": 2, "5": 1, "6": 2, "7": 2, "8": 2, "9": 1},
      "25":
          {"1": 2, "10": 2, "11": 1, "12": 2, "13": 2, "14": 1, "15": 2, "16": 2, "17": 2, "18": 2, "19": 2, "2": 1,
           "20": 2, "21": 2, "22": 2, "23": 1, "24": 2, "25": 1, "26": 2, "27": 2, "28": 1, "29": 2, "3": 2, "30": 1,
           "31": 2, "32": 2, "33": 1, "34": 2, "35": 1, "36": 1, "4": 1, "5": 1, "6": 2, "7": 2, "8": 2, "9": 2},
      "26":
          {"1": 2, "10": 1, "11": 1, "12": 1, "13": 2, "14": 1, "15": 2, "16": 1, "17": 1, "18": 2, "19": 2, "2": 2,
           "20": 1, "21": 2, "22": 2, "23": 1, "24": 1, "25": 1, "26": 1, "27": 2, "28": 2, "29": 1, "3": 1, "30": 1,
           "31": 1, "32": 1, "33": 2, "34": 1, "35": 2, "36": 2, "4": 2, "5": 2, "6": 1, "7": 1, "8": 1, "9": 2},
      "27":
          {"1": 2, "10": 2, "11": 2, "12": 2, "13": 1, "14": 2, "15": 2, "16": 2, "17": 2, "18": 1, "19": 1, "2": 2,
           "20": 1, "21": 2, "22": 1, "23": 1, "24": 2, "25": 1, "26": 1, "27": 2, "28": 1, "29": 1, "3": 2, "30": 2,
           "31": 1, "32": 1, "33": 1, "34": 1, "35": 2, "36": 1, "4": 1, "5": 1, "6": 1, "7": 1, "8": 2, "9": 2},
      "28":
          {"1": 1, "10": 1, "11": 1, "12": 1, "13": 1, "14": 1, "15": 2, "16": 2, "17": 1, "18": 2, "19": 2, "2": 1,
           "20": 1, "21": 2, "22": 1, "23": 2, "24": 2, "25": 1, "26": 1, "27": 1, "28": 2, "29": 2, "3": 2, "30": 2,
           "31": 1, "32": 1, "33": 2, "34": 2, "35": 2, "36": 1, "4": 2, "5": 1, "6": 2, "7": 2, "8": 1, "9": 2},
      "29":
          {"1": 1, "10": 1, "11": 2, "12": 1, "13": 2, "14": 2, "15": 2, "16": 2, "17": 2, "18": 1, "19": 1, "2": 1,
           "20": 1, "21": 2, "22": 1, "23": 1, "24": 2, "25": 2, "26": 2, "27": 1, "28": 1, "29": 1, "3": 2, "30": 1,
           "31": 2, "32": 1, "33": 2, "34": 2, "35": 2, "36": 1, "4": 1, "5": 1, "6": 1, "7": 1, "8": 2, "9": 2},
      "3":
          {"1": 1, "10": 2, "11": 2, "12": 2, "13": 1, "14": 1, "15": 1, "16": 1, "17": 1, "18": 2, "19": 2, "2": 2,
           "20": 1, "21": 1, "22": 1, "23": 2, "24": 1, "25": 1, "26": 2, "27": 1, "28": 1, "29": 1, "3": 1, "30": 1,
           "31": 1, "32": 2, "33": 1, "34": 1, "35": 1, "36": 1, "4": 2, "5": 2, "6": 2, "7": 2, "8": 2, "9": 2},
      "30":
          {"1": 2, "10": 1, "11": 1, "12": 2, "13": 2, "14": 2, "15": 2, "16": 2, "17": 2, "18": 1, "19": 2, "2": 1,
           "20": 2, "21": 2, "22": 1, "23": 1, "24": 1, "25": 1, "26": 1, "27": 2, "28": 1, "29": 1, "3": 1, "30": 1,
           "31": 2, "32": 1, "33": 1, "34": 1, "35": 2, "36": 2, "4": 1, "5": 2, "6": 2, "7": 2, "8": 1, "9": 1},
      "31":
          {"1": 1, "10": 2, "11": 2, "12": 2, "13": 1, "14": 1, "15": 2, "16": 2, "17": 2, "18": 1, "19": 1, "2": 1,
           "20": 1, "21": 2, "22": 1, "23": 2, "24": 1, "25": 2, "26": 2, "27": 1, "28": 1, "29": 2, "3": 1, "30": 1,
           "31": 1, "32": 2, "33": 2, "34": 2, "35": 1, "36": 1, "4": 1, "5": 2, "6": 1, "7": 2, "8": 2, "9": 2},
      "32":
          {"1": 1, "10": 1, "11": 2, "12": 2, "13": 1, "14": 2, "15": 1, "16": 1, "17": 1, "18": 2, "19": 1, "2": 2,
           "20": 1, "21": 2, "22": 2, "23": 1, "24": 2, "25": 1, "26": 2, "27": 1, "28": 2, "29": 2, "3": 1, "30": 2,
           "31": 2, "32": 1, "33": 1, "34": 2, "35": 2, "36": 2, "4": 2, "5": 2, "6": 1, "7": 2, "8": 2, "9": 1},
      "33":
          {"1": 2, "10": 2, "11": 1, "12": 2, "13": 2, "14": 1, "15": 1, "16": 2, "17": 2, "18": 1, "19": 2, "2": 1,
           "20": 1, "21": 1, "22": 1, "23": 1, "24": 1, "25": 1, "26": 1, "27": 2, "28": 2, "29": 1, "3": 1, "30": 1,
           "31": 2, "32": 2, "33": 1, "34": 1, "35": 1, "36": 1, "4": 2, "5": 1, "6": 1, "7": 1, "8": 1, "9": 2},
      "4":
          {"1": 1, "10": 2, "11": 2, "12": 2, "13": 1, "14": 2, "15": 1, "16": 1, "17": 2, "18": 2, "19": 1, "2": 2,
           "20": 1, "21": 2, "22": 1, "23": 2, "24": 1, "25": 1, "26": 1, "27": 1, "28": 2, "29": 1, "3": 1, "30": 1,
           "31": 1, "32": 1, "33": 2, "34": 2, "35": 2, "36": 2, "4": 2, "5": 2, "6": 1, "7": 2, "8": 1, "9": 1},
      "5":
          {"1": 1, "10": 1, "11": 1, "12": 2, "13": 1, "14": 1, "15": 1, "16": 1, "17": 1, "18": 2, "19": 1, "2": 1,
           "20": 1, "21": 1, "22": 1, "23": 1, "24": 1, "25": 1, "26": 2, "27": 2, "28": 1, "29": 2, "3": 2, "30": 1,
           "31": 1, "32": 2, "33": 2, "34": 1, "35": 1, "36": 1, "4": 2, "5": 1, "6": 1, "7": 2, "8": 1, "9": 2},
      "6":
          {"1": 2, "10": 2, "11": 2, "12": 1, "13": 2, "14": 2, "15": 2, "16": 2, "17": 1, "18": 2, "19": 1, "2": 1,
           "20": 1, "21": 2, "22": 2, "23": 2, "24": 2, "25": 1, "26": 2, "27": 1, "28": 1, "29": 2, "3": 2, "30": 1,
           "31": 1, "32": 2, "33": 2, "34": 1, "35": 2, "36": 1, "4": 2, "5": 1, "6": 2, "7": 2, "8": 1, "9": 1},
      "7":
          {"1": 1, "10": 2, "11": 2, "12": 2, "13": 2, "14": 1, "15": 2, "16": 1, "17": 2, "18": 1, "19": 2, "2": 1,
           "20": 1, "21": 2, "22": 1, "23": 1, "24": 2, "25": 2, "26": 1, "27": 1, "28": 2, "29": 2, "3": 1, "30": 2,
           "31": 2, "32": 1, "33": 1, "34": 2, "35": 1, "36": 1, "4": 1, "5": 1, "6": 1, "7": 2, "8": 2, "9": 2},
      "8":
          {"1": 2, "10": 2, "11": 2, "12": 1, "13": 2, "14": 1, "15": 2, "16": 2, "17": 1, "18": 2, "19": 2, "2": 1,
           "20": 2, "21": 1, "22": 2, "23": 2, "24": 1, "25": 2, "26": 1, "27": 2, "28": 1, "29": 2, "3": 2, "30": 2,
           "31": 2, "32": 2, "33": 1, "34": 1, "35": 1, "36": 2, "4": 1, "5": 1, "6": 2, "7": 1, "8": 2, "9": 2},
      "9":
          {"1": 2, "10": 1, "11": 1, "12": 1, "13": 2, "14": 1, "15": 1, "16": 1, "17": 1, "18": 2, "19": 1, "2": 1,
           "20": 2, "21": 2, "22": 2, "23": 2, "24": 1, "25": 2, "26": 2, "27": 1, "28": 1, "29": 2, "3": 2, "30": 1,
           "31": 2, "32": 2, "33": 2, "34": 1, "35": 2, "36": 2, "4": 2, "5": 2, "6": 2, "7": 1, "8": 1, "9": 2}},
 "demand_Function1D":
     {"1": 10, "10": 10, "11": 10, "2": 10, "3": 10, "4": 10, "5": 10, "6": 10, "7": 10, "8": 10, "9": 10},
 "fin1": 1188, "fin2": 2, "fin3": 396, "fin4": 1, "fin5": 33, "fin6": 32, "fin7": 11, "fin8": 10, "maxCost": 24,
 "n_customer": 11, "n_transshipment": 36, "n_warehouses": 33,
 "stock_Function1D":
     {"1": 27, "10": 30, "11": 27, "12": 32, "13": 29, "14": 30, "15": 28, "16": 28, "17": 29, "18": 29, "19": 26,
      "2": 26, "20": 29, "21": 32, "22": 28, "23": 31, "24": 26, "25": 28, "26": 32, "27": 31, "28": 30, "29": 26,
      "3": 27, "30": 32, "31": 26, "32": 31, "33": 32, "4": 27, "5": 29, "6": 29, "7": 29, "8": 27, "9": 28}}