{"class_Function1D":
     {"1": 6, "10": 4, "11": 9, "12": 10, "13": 1, "14": 6, "15": 10, "16": 7, "17": 6, "18": 5, "19": 8, "2": 6,
      "20": 10, "21": 9, "22": 4, "23": 2, "24": 6, "25": 8, "3": 6, "4": 3, "5": 6, "6": 2, "7": 10, "8": 2, "9": 1},
 "deck_length": 89, "deck_width": 41, "fin1": 25, "fin2": 25, "fin3": 25, "fin4": 1, "fin5": 64,
 "length_Function1D":
     {"1": 2, "10": 1, "11": 1, "12": 1, "13": 1, "14": 1, "15": 1, "16": 1, "17": 1, "18": 1, "19": 1, "2": 4, "20": 1,
      "21": 1, "22": 1, "23": 31, "24": 2, "25": 10, "3": 1, "4": 1, "5": 1, "6": 1, "7": 1, "8": 2, "9": 1},
 "n_classes": 10, "n_containers": 25,
 "separation_FunctionAsRelationR3_RelationAsSetR3_ExplicitR3_1_Explicit": {"1": {"1": 4, "2": 6}},
 "separation_FunctionAsRelationR3_RelationAsSetR3_ExplicitR3_2": {"1": 64},
 "width_Function1D":
     {"1": 1, "10": 39, "11": 14, "12": 7, "13": 37, "14": 7, "15": 31, "16": 14, "17": 7, "18": 1, "19": 24, "2": 1,
      "20": 12, "21": 5, "22": 24, "23": 40, "24": 28, "25": 40, "3": 32, "4": 25, "5": 22, "6": 25, "7": 11, "8": 35,
      "9": 7}}