{"costTC_FunctionND":
     {"1": {"1": 1, "2": 3}, "10": {"1": 2, "2": 1}, "11": {"1": 1, "2": 2}, "12": {"1": 1, "2": 3},
      "13": {"1": 2, "2": 1}, "14": {"1": 3, "2": 2}, "15": {"1": 1, "2": 2}, "16": {"1": 3, "2": 3},
      "17": {"1": 1, "2": 2}, "18": {"1": 3, "2": 1}, "19": {"1": 2, "2": 3}, "2": {"1": 1, "2": 1},
      "20": {"1": 3, "2": 1}, "21": {"1": 2, "2": 2}, "22": {"1": 2, "2": 2}, "23": {"1": 1, "2": 2},
      "24": {"1": 2, "2": 2}, "25": {"1": 3, "2": 2}, "26": {"1": 3, "2": 3}, "27": {"1": 1, "2": 1},
      "28": {"1": 2, "2": 1}, "29": {"1": 2, "2": 3}, "3": {"1": 1, "2": 1}, "30": {"1": 1, "2": 2},
      "31": {"1": 2, "2": 1}, "32": {"1": 2, "2": 2}, "33": {"1": 3, "2": 1}, "34": {"1": 1, "2": 1},
      "35": {"1": 3, "2": 3}, "36": {"1": 2, "2": 3}, "37": {"1": 2, "2": 3}, "38": {"1": 3, "2": 1},
      "39": {"1": 3, "2": 2}, "4": {"1": 1, "2": 1}, "40": {"1": 2, "2": 1}, "5": {"1": 1, "2": 1},
      "6": {"1": 1, "2": 3}, "7": {"1": 3, "2": 2}, "8": {"1": 2, "2": 2}, "9": {"1": 1, "2": 2}},
 "costWT_FunctionND":
     {"1":
          {"1": 1, "10": 1, "11": 1, "12": 1, "13": 1, "14": 1, "15": 1, "16": 1, "17": 1, "18": 1, "19": 1, "2": 1,
           "20": 1, "21": 1, "22": 1, "23": 1, "24": 1, "25": 1, "26": 1, "27": 1, "28": 1, "29": 1, "3": 1, "30": 1,
           "31": 1, "32": 1, "33": 1, "34": 1, "35": 1, "36": 1, "37": 1, "38": 1, "39": 1, "4": 1, "40": 1, "5": 1,
           "6": 1, "7": 1, "8": 1, "9": 1},
      "10":
          {"1": 1, "10": 1, "11": 1, "12": 1, "13": 1, "14": 1, "15": 1, "16": 1, "17": 1, "18": 1, "19": 1, "2": 1,
           "20": 1, "21": 1, "22": 1, "23": 1, "24": 1, "25": 1, "26": 1, "27": 1, "28": 1, "29": 1, "3": 1, "30": 1,
           "31": 1, "32": 1, "33": 1, "34": 1, "35": 1, "36": 1, "37": 1, "38": 1, "39": 1, "4": 1, "40": 1, "5": 1,
           "6": 1, "7": 1, "8": 1, "9": 1},
      "11":
          {"1": 1, "10": 1, "11": 1, "12": 1, "13": 1, "14": 1, "15": 1, "16": 1, "17": 1, "18": 1, "19": 1, "2": 1,
           "20": 1, "21": 1, "22": 1, "23": 1, "24": 1, "25": 1, "26": 1, "27": 1, "28": 1, "29": 1, "3": 1, "30": 1,
           "31": 1, "32": 1, "33": 1, "34": 1, "35": 1, "36": 1, "37": 1, "38": 1, "39": 1, "4": 1, "40": 1, "5": 1,
           "6": 1, "7": 1, "8": 1, "9": 1},
      "12":
          {"1": 1, "10": 1, "11": 1, "12": 1, "13": 1, "14": 1, "15": 1, "16": 1, "17": 1, "18": 1, "19": 1, "2": 1,
           "20": 1, "21": 1, "22": 1, "23": 1, "24": 1, "25": 1, "26": 1, "27": 1, "28": 1, "29": 1, "3": 1, "30": 1,
           "31": 1, "32": 1, "33": 1, "34": 1, "35": 1, "36": 1, "37": 1, "38": 1, "39": 1, "4": 1, "40": 1, "5": 1,
           "6": 1, "7": 1, "8": 1, "9": 1},
      "13":
          {"1": 1, "10": 1, "11": 1, "12": 1, "13": 1, "14": 1, "15": 1, "16": 1, "17": 1, "18": 1, "19": 1, "2": 1,
           "20": 1, "21": 1, "22": 1, "23": 1, "24": 1, "25": 1, "26": 1, "27": 1, "28": 1, "29": 1, "3": 1, "30": 1,
           "31": 1, "32": 1, "33": 1, "34": 1, "35": 1, "36": 1, "37": 1, "38": 1, "39": 1, "4": 1, "40": 1, "5": 1,
           "6": 1, "7": 1, "8": 1, "9": 1},
      "14":
          {"1": 1, "10": 1, "11": 1, "12": 1, "13": 1, "14": 1, "15": 1, "16": 1, "17": 1, "18": 1, "19": 1, "2": 1,
           "20": 1, "21": 1, "22": 1, "23": 1, "24": 1, "25": 1, "26": 1, "27": 1, "28": 1, "29": 1, "3": 1, "30": 1,
           "31": 1, "32": 1, "33": 1, "34": 1, "35": 1, "36": 1, "37": 1, "38": 1, "39": 1, "4": 1, "40": 1, "5": 1,
           "6": 1, "7": 1, "8": 1, "9": 1},
      "15":
          {"1": 1, "10": 1, "11": 1, "12": 1, "13": 1, "14": 1, "15": 1, "16": 1, "17": 1, "18": 1, "19": 1, "2": 1,
           "20": 1, "21": 1, "22": 1, "23": 1, "24": 1, "25": 1, "26": 1, "27": 1, "28": 1, "29": 1, "3": 1, "30": 1,
           "31": 1, "32": 1, "33": 1, "34": 1, "35": 1, "36": 1, "37": 1, "38": 1, "39": 1, "4": 1, "40": 1, "5": 1,
           "6": 1, "7": 1, "8": 1, "9": 1},
      "16":
          {"1": 1, "10": 1, "11": 1, "12": 1, "13": 1, "14": 1, "15": 1, "16": 1, "17": 1, "18": 1, "19": 1, "2": 1,
           "20": 1, "21": 1, "22": 1, "23": 1, "24": 1, "25": 1, "26": 1, "27": 1, "28": 1, "29": 1, "3": 1, "30": 1,
           "31": 1, "32": 1, "33": 1, "34": 1, "35": 1, "36": 1, "37": 1, "38": 1, "39": 1, "4": 1, "40": 1, "5": 1,
           "6": 1, "7": 1, "8": 1, "9": 1},
      "17":
          {"1": 1, "10": 1, "11": 1, "12": 1, "13": 1, "14": 1, "15": 1, "16": 1, "17": 1, "18": 1, "19": 1, "2": 1,
           "20": 1, "21": 1, "22": 1, "23": 1, "24": 1, "25": 1, "26": 1, "27": 1, "28": 1, "29": 1, "3": 1, "30": 1,
           "31": 1, "32": 1, "33": 1, "34": 1, "35": 1, "36": 1, "37": 1, "38": 1, "39": 1, "4": 1, "40": 1, "5": 1,
           "6": 1, "7": 1, "8": 1, "9": 1},
      "18":
          {"1": 1, "10": 1, "11": 1, "12": 1, "13": 1, "14": 1, "15": 1, "16": 1, "17": 1, "18": 1, "19": 1, "2": 1,
           "20": 1, "21": 1, "22": 1, "23": 1, "24": 1, "25": 1, "26": 1, "27": 1, "28": 1, "29": 1, "3": 1, "30": 1,
           "31": 1, "32": 1, "33": 1, "34": 1, "35": 1, "36": 1, "37": 1, "38": 1, "39": 1, "4": 1, "40": 1, "5": 1,
           "6": 1, "7": 1, "8": 1, "9": 1},
      "19":
          {"1": 1, "10": 1, "11": 1, "12": 1, "13": 1, "14": 1, "15": 1, "16": 1, "17": 1, "18": 1, "19": 1, "2": 1,
           "20": 1, "21": 1, "22": 1, "23": 1, "24": 1, "25": 1, "26": 1, "27": 1, "28": 1, "29": 1, "3": 1, "30": 1,
           "31": 1, "32": 1, "33": 1, "34": 1, "35": 1, "36": 1, "37": 1, "38": 1, "39": 1, "4": 1, "40": 1, "5": 1,
           "6": 1, "7": 1, "8": 1, "9": 1},
      "2":
          {"1": 1, "10": 1, "11": 1, "12": 1, "13": 1, "14": 1, "15": 1, "16": 1, "17": 1, "18": 1, "19": 1, "2": 1,
           "20": 1, "21": 1, "22": 1, "23": 1, "24": 1, "25": 1, "26": 1, "27": 1, "28": 1, "29": 1, "3": 1, "30": 1,
           "31": 1, "32": 1, "33": 1, "34": 1, "35": 1, "36": 1, "37": 1, "38": 1, "39": 1, "4": 1, "40": 1, "5": 1,
           "6": 1, "7": 1, "8": 1, "9": 1},
      "20":
          {"1": 1, "10": 1, "11": 1, "12": 1, "13": 1, "14": 1, "15": 1, "16": 1, "17": 1, "18": 1, "19": 1, "2": 1,
           "20": 1, "21": 1, "22": 1, "23": 1, "24": 1, "25": 1, "26": 1, "27": 1, "28": 1, "29": 1, "3": 1, "30": 1,
           "31": 1, "32": 1, "33": 1, "34": 1, "35": 1, "36": 1, "37": 1, "38": 1, "39": 1, "4": 1, "40": 1, "5": 1,
           "6": 1, "7": 1, "8": 1, "9": 1},
      "21":
          {"1": 1, "10": 1, "11": 1, "12": 1, "13": 1, "14": 1, "15": 1, "16": 1, "17": 1, "18": 1, "19": 1, "2": 1,
           "20": 1, "21": 1, "22": 1, "23": 1, "24": 1, "25": 1, "26": 1, "27": 1, "28": 1, "29": 1, "3": 1, "30": 1,
           "31": 1, "32": 1, "33": 1, "34": 1, "35": 1, "36": 1, "37": 1, "38": 1, "39": 1, "4": 1, "40": 1, "5": 1,
           "6": 1, "7": 1, "8": 1, "9": 1},
      "22":
          {"1": 1, "10": 1, "11": 1, "12": 1, "13": 1, "14": 1, "15": 1, "16": 1, "17": 1, "18": 1, "19": 1, "2": 1,
           "20": 1, "21": 1, "22": 1, "23": 1, "24": 1, "25": 1, "26": 1, "27": 1, "28": 1, "29": 1, "3": 1, "30": 1,
           "31": 1, "32": 1, "33": 1, "34": 1, "35": 1, "36": 1, "37": 1, "38": 1, "39": 1, "4": 1, "40": 1, "5": 1,
           "6": 1, "7": 1, "8": 1, "9": 1},
      "23":
          {"1": 1, "10": 1, "11": 1, "12": 1, "13": 1, "14": 1, "15": 1, "16": 1, "17": 1, "18": 1, "19": 1, "2": 1,
           "20": 1, "21": 1, "22": 1, "23": 1, "24": 1, "25": 1, "26": 1, "27": 1, "28": 1, "29": 1, "3": 1, "30": 1,
           "31": 1, "32": 1, "33": 1, "34": 1, "35": 1, "36": 1, "37": 1, "38": 1, "39": 1, "4": 1, "40": 1, "5": 1,
           "6": 1, "7": 1, "8": 1, "9": 1},
      "24":
          {"1": 1, "10": 1, "11": 1, "12": 1, "13": 1, "14": 1, "15": 1, "16": 1, "17": 1, "18": 1, "19": 1, "2": 1,
           "20": 1, "21": 1, "22": 1, "23": 1, "24": 1, "25": 1, "26": 1, "27": 1, "28": 1, "29": 1, "3": 1, "30": 1,
           "31": 1, "32": 1, "33": 1, "34": 1, "35": 1, "36": 1, "37": 1, "38": 1, "39": 1, "4": 1, "40": 1, "5": 1,
           "6": 1, "7": 1, "8": 1, "9": 1},
      "25":
          {"1": 1, "10": 1, "11": 1, "12": 1, "13": 1, "14": 1, "15": 1, "16": 1, "17": 1, "18": 1, "19": 1, "2": 1,
           "20": 1, "21": 1, "22": 1, "23": 1, "24": 1, "25": 1, "26": 1, "27": 1, "28": 1, "29": 1, "3": 1, "30": 1,
           "31": 1, "32": 1, "33": 1, "34": 1, "35": 1, "36": 1, "37": 1, "38": 1, "39": 1, "4": 1, "40": 1, "5": 1,
           "6": 1, "7": 1, "8": 1, "9": 1},
      "26":
          {"1": 1, "10": 1, "11": 1, "12": 1, "13": 1, "14": 1, "15": 1, "16": 1, "17": 1, "18": 1, "19": 1, "2": 1,
           "20": 1, "21": 1, "22": 1, "23": 1, "24": 1, "25": 1, "26": 1, "27": 1, "28": 1, "29": 1, "3": 1, "30": 1,
           "31": 1, "32": 1, "33": 1, "34": 1, "35": 1, "36": 1, "37": 1, "38": 1, "39": 1, "4": 1, "40": 1, "5": 1,
           "6": 1, "7": 1, "8": 1, "9": 1},
      "27":
          {"1": 1, "10": 1, "11": 1, "12": 1, "13": 1, "14": 1, "15": 1, "16": 1, "17": 1, "18": 1, "19": 1, "2": 1,
           "20": 1, "21": 1, "22": 1, "23": 1, "24": 1, "25": 1, "26": 1, "27": 1, "28": 1, "29": 1, "3": 1, "30": 1,
           "31": 1, "32": 1, "33": 1, "34": 1, "35": 1, "36": 1, "37": 1, "38": 1, "39": 1, "4": 1, "40": 1, "5": 1,
           "6": 1, "7": 1, "8": 1, "9": 1},
      "28":
          {"1": 1, "10": 1, "11": 1, "12": 1, "13": 1, "14": 1, "15": 1, "16": 1, "17": 1, "18": 1, "19": 1, "2": 1,
           "20": 1, "21": 1, "22": 1, "23": 1, "24": 1, "25": 1, "26": 1, "27": 1, "28": 1, "29": 1, "3": 1, "30": 1,
           "31": 1, "32": 1, "33": 1, "34": 1, "35": 1, "36": 1, "37": 1, "38": 1, "39": 1, "4": 1, "40": 1, "5": 1,
           "6": 1, "7": 1, "8": 1, "9": 1},
      "29":
          {"1": 1, "10": 1, "11": 1, "12": 1, "13": 1, "14": 1, "15": 1, "16": 1, "17": 1, "18": 1, "19": 1, "2": 1,
           "20": 1, "21": 1, "22": 1, "23": 1, "24": 1, "25": 1, "26": 1, "27": 1, "28": 1, "29": 1, "3": 1, "30": 1,
           "31": 1, "32": 1, "33": 1, "34": 1, "35": 1, "36": 1, "37": 1, "38": 1, "39": 1, "4": 1, "40": 1, "5": 1,
           "6": 1, "7": 1, "8": 1, "9": 1},
      "3":
          {"1": 1, "10": 1, "11": 1, "12": 1, "13": 1, "14": 1, "15": 1, "16": 1, "17": 1, "18": 1, "19": 1, "2": 1,
           "20": 1, "21": 1, "22": 1, "23": 1, "24": 1, "25": 1, "26": 1, "27": 1, "28": 1, "29": 1, "3": 1, "30": 1,
           "31": 1, "32": 1, "33": 1, "34": 1, "35": 1, "36": 1, "37": 1, "38": 1, "39": 1, "4": 1, "40": 1, "5": 1,
           "6": 1, "7": 1, "8": 1, "9": 1},
      "30":
          {"1": 1, "10": 1, "11": 1, "12": 1, "13": 1, "14": 1, "15": 1, "16": 1, "17": 1, "18": 1, "19": 1, "2": 1,
           "20": 1, "21": 1, "22": 1, "23": 1, "24": 1, "25": 1, "26": 1, "27": 1, "28": 1, "29": 1, "3": 1, "30": 1,
           "31": 1, "32": 1, "33": 1, "34": 1, "35": 1, "36": 1, "37": 1, "38": 1, "39": 1, "4": 1, "40": 1, "5": 1,
           "6": 1, "7": 1, "8": 1, "9": 1},
      "31":
          {"1": 1, "10": 1, "11": 1, "12": 1, "13": 1, "14": 1, "15": 1, "16": 1, "17": 1, "18": 1, "19": 1, "2": 1,
           "20": 1, "21": 1, "22": 1, "23": 1, "24": 1, "25": 1, "26": 1, "27": 1, "28": 1, "29": 1, "3": 1, "30": 1,
           "31": 1, "32": 1, "33": 1, "34": 1, "35": 1, "36": 1, "37": 1, "38": 1, "39": 1, "4": 1, "40": 1, "5": 1,
           "6": 1, "7": 1, "8": 1, "9": 1},
      "32":
          {"1": 1, "10": 1, "11": 1, "12": 1, "13": 1, "14": 1, "15": 1, "16": 1, "17": 1, "18": 1, "19": 1, "2": 1,
           "20": 1, "21": 1, "22": 1, "23": 1, "24": 1, "25": 1, "26": 1, "27": 1, "28": 1, "29": 1, "3": 1, "30": 1,
           "31": 1, "32": 1, "33": 1, "34": 1, "35": 1, "36": 1, "37": 1, "38": 1, "39": 1, "4": 1, "40": 1, "5": 1,
           "6": 1, "7": 1, "8": 1, "9": 1},
      "33":
          {"1": 1, "10": 1, "11": 1, "12": 1, "13": 1, "14": 1, "15": 1, "16": 1, "17": 1, "18": 1, "19": 1, "2": 1,
           "20": 1, "21": 1, "22": 1, "23": 1, "24": 1, "25": 1, "26": 1, "27": 1, "28": 1, "29": 1, "3": 1, "30": 1,
           "31": 1, "32": 1, "33": 1, "34": 1, "35": 1, "36": 1, "37": 1, "38": 1, "39": 1, "4": 1, "40": 1, "5": 1,
           "6": 1, "7": 1, "8": 1, "9": 1},
      "34":
          {"1": 1, "10": 1, "11": 1, "12": 1, "13": 1, "14": 1, "15": 1, "16": 1, "17": 1, "18": 1, "19": 1, "2": 1,
           "20": 1, "21": 1, "22": 1, "23": 1, "24": 1, "25": 1, "26": 1, "27": 1, "28": 1, "29": 1, "3": 1, "30": 1,
           "31": 1, "32": 1, "33": 1, "34": 1, "35": 1, "36": 1, "37": 1, "38": 1, "39": 1, "4": 1, "40": 1, "5": 1,
           "6": 1, "7": 1, "8": 1, "9": 1},
      "35":
          {"1": 1, "10": 1, "11": 1, "12": 1, "13": 1, "14": 1, "15": 1, "16": 1, "17": 1, "18": 1, "19": 1, "2": 1,
           "20": 1, "21": 1, "22": 1, "23": 1, "24": 1, "25": 1, "26": 1, "27": 1, "28": 1, "29": 1, "3": 1, "30": 1,
           "31": 1, "32": 1, "33": 1, "34": 1, "35": 1, "36": 1, "37": 1, "38": 1, "39": 1, "4": 1, "40": 1, "5": 1,
           "6": 1, "7": 1, "8": 1, "9": 1},
      "36":
          {"1": 1, "10": 1, "11": 1, "12": 1, "13": 1, "14": 1, "15": 1, "16": 1, "17": 1, "18": 1, "19": 1, "2": 1,
           "20": 1, "21": 1, "22": 1, "23": 1, "24": 1, "25": 1, "26": 1, "27": 1, "28": 1, "29": 1, "3": 1, "30": 1,
           "31": 1, "32": 1, "33": 1, "34": 1, "35": 1, "36": 1, "37": 1, "38": 1, "39": 1, "4": 1, "40": 1, "5": 1,
           "6": 1, "7": 1, "8": 1, "9": 1},
      "4":
          {"1": 1, "10": 1, "11": 1, "12": 1, "13": 1, "14": 1, "15": 1, "16": 1, "17": 1, "18": 1, "19": 1, "2": 1,
           "20": 1, "21": 1, "22": 1, "23": 1, "24": 1, "25": 1, "26": 1, "27": 1, "28": 1, "29": 1, "3": 1, "30": 1,
           "31": 1, "32": 1, "33": 1, "34": 1, "35": 1, "36": 1, "37": 1, "38": 1, "39": 1, "4": 1, "40": 1, "5": 1,
           "6": 1, "7": 1, "8": 1, "9": 1},
      "5":
          {"1": 1, "10": 1, "11": 1, "12": 1, "13": 1, "14": 1, "15": 1, "16": 1, "17": 1, "18": 1, "19": 1, "2": 1,
           "20": 1, "21": 1, "22": 1, "23": 1, "24": 1, "25": 1, "26": 1, "27": 1, "28": 1, "29": 1, "3": 1, "30": 1,
           "31": 1, "32": 1, "33": 1, "34": 1, "35": 1, "36": 1, "37": 1, "38": 1, "39": 1, "4": 1, "40": 1, "5": 1,
           "6": 1, "7": 1, "8": 1, "9": 1},
      "6":
          {"1": 1, "10": 1, "11": 1, "12": 1, "13": 1, "14": 1, "15": 1, "16": 1, "17": 1, "18": 1, "19": 1, "2": 1,
           "20": 1, "21": 1, "22": 1, "23": 1, "24": 1, "25": 1, "26": 1, "27": 1, "28": 1, "29": 1, "3": 1, "30": 1,
           "31": 1, "32": 1, "33": 1, "34": 1, "35": 1, "36": 1, "37": 1, "38": 1, "39": 1, "4": 1, "40": 1, "5": 1,
           "6": 1, "7": 1, "8": 1, "9": 1},
      "7":
          {"1": 1, "10": 1, "11": 1, "12": 1, "13": 1, "14": 1, "15": 1, "16": 1, "17": 1, "18": 1, "19": 1, "2": 1,
           "20": 1, "21": 1, "22": 1, "23": 1, "24": 1, "25": 1, "26": 1, "27": 1, "28": 1, "29": 1, "3": 1, "30": 1,
           "31": 1, "32": 1, "33": 1, "34": 1, "35": 1, "36": 1, "37": 1, "38": 1, "39": 1, "4": 1, "40": 1, "5": 1,
           "6": 1, "7": 1, "8": 1, "9": 1},
      "8":
          {"1": 1, "10": 1, "11": 1, "12": 1, "13": 1, "14": 1, "15": 1, "16": 1, "17": 1, "18": 1, "19": 1, "2": 1,
           "20": 1, "21": 1, "22": 1, "23": 1, "24": 1, "25": 1, "26": 1, "27": 1, "28": 1, "29": 1, "3": 1, "30": 1,
           "31": 1, "32": 1, "33": 1, "34": 1, "35": 1, "36": 1, "37": 1, "38": 1, "39": 1, "4": 1, "40": 1, "5": 1,
           "6": 1, "7": 1, "8": 1, "9": 1},
      "9":
          {"1": 1, "10": 1, "11": 1, "12": 1, "13": 1, "14": 1, "15": 1, "16": 1, "17": 1, "18": 1, "19": 1, "2": 1,
           "20": 1, "21": 1, "22": 1, "23": 1, "24": 1, "25": 1, "26": 1, "27": 1, "28": 1, "29": 1, "3": 1, "30": 1,
           "31": 1, "32": 1, "33": 1, "34": 1, "35": 1, "36": 1, "37": 1, "38": 1, "39": 1, "4": 1, "40": 1, "5": 1,
           "6": 1, "7": 1, "8": 1, "9": 1}},
 "demand_Function1D": {"1": 22, "2": 26}, "fin1": 1440, "fin2": 1, "fin3": 80, "fin4": 3, "fin5": 36, "fin6": 36,
 "fin7": 2, "fin8": 26, "maxCost": 43, "n_customer": 2, "n_transshipment": 40, "n_warehouses": 36,
 "stock_Function1D":
     {"1": 36, "10": 36, "11": 34, "12": 35, "13": 36, "14": 35, "15": 36, "16": 34, "17": 35, "18": 36, "19": 36,
      "2": 34, "20": 36, "21": 34, "22": 35, "23": 36, "24": 36, "25": 34, "26": 36, "27": 34, "28": 34, "29": 35,
      "3": 35, "30": 35, "31": 35, "32": 36, "33": 36, "34": 36, "35": 35, "36": 34, "4": 34, "5": 35, "6": 34, "7": 36,
      "8": 35, "9": 35}}