{"blksize_delta_Function1D": {"1": 8, "10": 9, "11": 8, "2": 8, "3": 9, "4": 8, "5": 8, "6": 8, "7": 8, "8": 8, "9": 8},
 "fin1": 61, "fin2": 10, "fin3": 11, "fin4": 9, "fin5": 11, "fin6": 9, "fin7": 94,
 "maxcars_Function1D": {"1": 9, "10": 9, "11": 9, "2": 9, "3": 9, "4": 9, "5": 9, "6": 9, "7": 9, "8": 9, "9": 9},
 "n_cars": 253, "n_classes": 61, "n_options": 11,
 "quantity_Function1D":
     {"1": 4, "10": 4, "11": 4, "12": 4, "13": 4, "14": 4, "15": 4, "16": 5, "17": 4, "18": 4, "19": 4, "2": 4, "20": 4,
      "21": 4, "22": 4, "23": 4, "24": 4, "25": 4, "26": 4, "27": 4, "28": 4, "29": 4, "3": 4, "30": 5, "31": 4,
      "32": 4, "33": 4, "34": 4, "35": 4, "36": 4, "37": 4, "38": 4, "39": 4, "4": 4, "40": 4, "41": 4, "42": 4,
      "43": 4, "44": 4, "45": 4, "46": 4, "47": 4, "48": 4, "49": 4, "5": 5, "50": 4, "51": 4, "52": 4, "53": 4,
      "54": 4, "55": 4, "56": 4, "57": 4, "58": 4, "59": 4, "6": 10, "60": 4, "61": 4, "7": 4, "8": 4, "9": 4},
 "usage_RelationAsSet_Explicit_1":
     {"1": 1, "10": 5, "11": 6, "12": 6, "13": 7, "14": 8, "15": 9, "16": 10, "17": 10, "18": 10, "19": 11, "2": 1,
      "20": 12, "21": 13, "22": 13, "23": 13, "24": 14, "25": 15, "26": 16, "27": 17, "28": 17, "29": 17, "3": 1,
      "30": 18, "31": 19, "32": 19, "33": 20, "34": 21, "35": 22, "36": 23, "37": 24, "38": 25, "39": 25, "4": 1,
      "40": 25, "41": 26, "42": 26, "43": 27, "44": 28, "45": 29, "46": 30, "47": 30, "48": 31, "49": 32, "5": 2,
      "50": 33, "51": 33, "52": 33, "53": 34, "54": 35, "55": 36, "56": 37, "57": 38, "58": 38, "59": 38, "6": 3,
      "60": 39, "61": 40, "62": 41, "63": 42, "64": 42, "65": 43, "66": 44, "67": 45, "68": 46, "69": 46, "7": 4,
      "70": 47, "71": 48, "72": 48, "73": 48, "74": 49, "75": 49, "76": 50, "77": 50, "78": 51, "79": 51, "8": 4,
      "80": 52, "81": 52, "82": 52, "83": 53, "84": 54, "85": 55, "86": 56, "87": 56, "88": 56, "89": 56, "9": 4,
      "90": 57, "91": 58, "92": 59, "93": 60, "94": 61},
 "usage_RelationAsSet_Explicit_2":
     {"1": 6, "10": 3, "11": 1, "12": 11, "13": 4, "14": 6, "15": 1, "16": 8, "17": 9, "18": 10, "19": 9, "2": 8,
      "20": 9, "21": 3, "22": 7, "23": 10, "24": 1, "25": 4, "26": 7, "27": 2, "28": 4, "29": 6, "3": 10, "30": 5,
      "31": 1, "32": 4, "33": 11, "34": 11, "35": 5, "36": 9, "37": 11, "38": 3, "39": 5, "4": 11, "40": 9, "41": 4,
      "42": 6, "43": 11, "44": 11, "45": 5, "46": 4, "47": 5, "48": 1, "49": 11, "5": 11, "50": 2, "51": 5, "52": 6,
      "53": 8, "54": 11, "55": 9, "56": 4, "57": 2, "58": 3, "59": 10, "6": 11, "60": 11, "61": 2, "62": 11, "63": 7,
      "64": 8, "65": 1, "66": 6, "67": 2, "68": 2, "69": 3, "7": 5, "70": 11, "71": 4, "72": 5, "73": 9, "74": 8,
      "75": 10, "76": 5, "77": 6, "78": 2, "79": 9, "8": 6, "80": 1, "81": 7, "82": 10, "83": 7, "84": 10, "85": 2,
      "86": 1, "87": 4, "88": 6, "89": 10, "9": 10, "90": 1, "91": 11, "92": 11, "93": 10, "94": 11}}