{"blksize_delta_Function1D":
     {"1": 8, "10": 8, "11": 8, "12": 8, "13": 8, "14": 10, "15": 8, "16": 8, "2": 8, "3": 8, "4": 10, "5": 10, "6": 8,
      "7": 9, "8": 10, "9": 8},
 "fin1": 33, "fin2": 22, "fin3": 16, "fin4": 10, "fin5": 16, "fin6": 10, "fin7": 130,
 "maxcars_Function1D":
     {"1": 10, "10": 10, "11": 10, "12": 10, "13": 10, "14": 10, "15": 10, "16": 10, "2": 10, "3": 10, "4": 10, "5": 10,
      "6": 10, "7": 10, "8": 10, "9": 10},
 "n_cars": 217, "n_classes": 33, "n_options": 16,
 "quantity_Function1D":
     {"1": 6, "10": 7, "11": 6, "12": 6, "13": 6, "14": 6, "15": 6, "16": 6, "17": 6, "18": 6, "19": 6, "2": 8, "20": 6,
      "21": 6, "22": 6, "23": 6, "24": 6, "25": 6, "26": 6, "27": 6, "28": 6, "29": 6, "3": 22, "30": 6, "31": 6,
      "32": 6, "33": 6, "4": 6, "5": 6, "6": 6, "7": 6, "8": 6, "9": 6},
 "usage_RelationAsSet_Explicit_1":
     {"1": 1, "10": 3, "100": 26, "101": 26, "102": 27, "103": 27, "104": 27, "105": 27, "106": 28, "107": 28,
      "108": 29, "109": 29, "11": 3, "110": 30, "111": 30, "112": 30, "113": 30, "114": 30, "115": 30, "116": 31,
      "117": 31, "118": 31, "119": 31, "12": 3, "120": 31, "121": 31, "122": 31, "123": 32, "124": 32, "125": 32,
      "126": 32, "127": 33, "128": 33, "129": 33, "13": 3, "130": 33, "14": 4, "15": 4, "16": 4, "17": 5, "18": 5,
      "19": 6, "2": 1, "20": 7, "21": 7, "22": 7, "23": 7, "24": 8, "25": 8, "26": 8, "27": 8, "28": 8, "29": 8, "3": 2,
      "30": 8, "31": 9, "32": 9, "33": 9, "34": 10, "35": 10, "36": 10, "37": 10, "38": 11, "39": 11, "4": 2, "40": 11,
      "41": 11, "42": 11, "43": 11, "44": 12, "45": 12, "46": 12, "47": 12, "48": 13, "49": 13, "5": 2, "50": 13,
      "51": 13, "52": 13, "53": 14, "54": 14, "55": 14, "56": 15, "57": 16, "58": 16, "59": 16, "6": 2, "60": 16,
      "61": 17, "62": 17, "63": 18, "64": 18, "65": 19, "66": 19, "67": 19, "68": 19, "69": 19, "7": 2, "70": 20,
      "71": 20, "72": 20, "73": 20, "74": 20, "75": 21, "76": 21, "77": 21, "78": 21, "79": 21, "8": 2, "80": 21,
      "81": 22, "82": 22, "83": 22, "84": 23, "85": 23, "86": 23, "87": 23, "88": 24, "89": 24, "9": 3, "90": 24,
      "91": 25, "92": 25, "93": 25, "94": 25, "95": 25, "96": 25, "97": 26, "98": 26, "99": 26},
 "usage_RelationAsSet_Explicit_2":
     {"1": 5, "10": 8, "100": 10, "101": 11, "102": 2, "103": 6, "104": 13, "105": 15, "106": 10, "107": 13, "108": 3,
      "109": 16, "11": 9, "110": 1, "111": 2, "112": 3, "113": 10, "114": 14, "115": 16, "116": 3, "117": 5, "118": 7,
      "119": 8, "12": 12, "120": 10, "121": 12, "122": 14, "123": 2, "124": 3, "125": 4, "126": 13, "127": 1, "128": 6,
      "129": 10, "13": 13, "130": 15, "14": 2, "15": 3, "16": 5, "17": 9, "18": 16, "19": 16, "2": 11, "20": 1,
      "21": 11, "22": 14, "23": 15, "24": 1, "25": 3, "26": 5, "27": 9, "28": 12, "29": 14, "3": 2, "30": 16, "31": 6,
      "32": 7, "33": 15, "34": 1, "35": 2, "36": 3, "37": 4, "38": 1, "39": 2, "4": 3, "40": 4, "41": 5, "42": 7,
      "43": 9, "44": 3, "45": 5, "46": 10, "47": 12, "48": 4, "49": 9, "5": 7, "50": 10, "51": 12, "52": 15, "53": 4,
      "54": 9, "55": 16, "56": 5, "57": 5, "58": 6, "59": 7, "6": 9, "60": 11, "61": 3, "62": 14, "63": 2, "64": 4,
      "65": 4, "66": 6, "67": 8, "68": 11, "69": 14, "7": 13, "70": 1, "71": 2, "72": 7, "73": 9, "74": 15, "75": 2,
      "76": 3, "77": 8, "78": 12, "79": 15, "8": 16, "80": 16, "81": 6, "82": 9, "83": 13, "84": 5, "85": 8, "86": 10,
      "87": 14, "88": 6, "89": 7, "9": 7, "90": 10, "91": 1, "92": 3, "93": 4, "94": 6, "95": 9, "96": 10, "97": 3,
      "98": 4, "99": 9}}