{"blksize_delta_Function1D": {"1": 7, "2": 7, "3": 7, "4": 7, "5": 7, "6": 7}, "fin1": 100, "fin2": 51, "fin3": 6,
 "fin4": 10, "fin5": 6, "fin6": 7, "fin7": 155,
 "maxcars_Function1D": {"1": 10, "2": 10, "3": 10, "4": 10, "5": 10, "6": 10}, "n_cars": 291, "n_classes": 100,
 "n_options": 6,
 "quantity_Function1D":
     {"1": 51, "10": 2, "100": 2, "11": 2, "12": 2, "13": 3, "14": 2, "15": 2, "16": 2, "17": 2, "18": 2, "19": 2,
      "2": 2, "20": 2, "21": 2, "22": 2, "23": 2, "24": 2, "25": 2, "26": 2, "27": 2, "28": 2, "29": 2, "3": 2, "30": 2,
      "31": 2, "32": 2, "33": 2, "34": 2, "35": 2, "36": 2, "37": 2, "38": 2, "39": 2, "4": 2, "40": 2, "41": 2,
      "42": 2, "43": 2, "44": 2, "45": 2, "46": 2, "47": 2, "48": 2, "49": 2, "5": 36, "50": 2, "51": 2, "52": 2,
      "53": 2, "54": 2, "55": 2, "56": 2, "57": 2, "58": 2, "59": 2, "6": 2, "60": 2, "61": 2, "62": 2, "63": 2,
      "64": 2, "65": 2, "66": 2, "67": 2, "68": 2, "69": 2, "7": 6, "70": 2, "71": 2, "72": 2, "73": 2, "74": 2,
      "75": 2, "76": 2, "77": 2, "78": 2, "79": 2, "8": 2, "80": 2, "81": 2, "82": 2, "83": 2, "84": 2, "85": 2,
      "86": 2, "87": 2, "88": 2, "89": 2, "9": 5, "90": 2, "91": 2, "92": 2, "93": 2, "94": 2, "95": 2, "96": 2,
      "97": 2, "98": 2, "99": 2},
 "usage_RelationAsSet_Explicit_1":
     {"1": 1, "10": 5, "100": 65, "101": 65, "102": 66, "103": 67, "104": 67, "105": 68, "106": 69, "107": 70,
      "108": 71, "109": 72, "11": 6, "110": 73, "111": 73, "112": 73, "113": 73, "114": 74, "115": 75, "116": 76,
      "117": 76, "118": 77, "119": 78, "12": 7, "120": 79, "121": 80, "122": 80, "123": 81, "124": 81, "125": 82,
      "126": 82, "127": 82, "128": 82, "129": 83, "13": 8, "130": 84, "131": 84, "132": 84, "133": 85, "134": 86,
      "135": 86, "136": 87, "137": 87, "138": 87, "139": 88, "14": 9, "140": 89, "141": 90, "142": 91, "143": 92,
      "144": 93, "145": 93, "146": 94, "147": 94, "148": 95, "149": 96, "15": 9, "150": 97, "151": 97, "152": 98,
      "153": 99, "154": 100, "155": 100, "16": 9, "17": 10, "18": 10, "19": 11, "2": 2, "20": 11, "21": 12, "22": 13,
      "23": 14, "24": 15, "25": 15, "26": 16, "27": 17, "28": 17, "29": 17, "3": 3, "30": 18, "31": 18, "32": 19,
      "33": 19, "34": 19, "35": 19, "36": 20, "37": 20, "38": 20, "39": 21, "4": 3, "40": 22, "41": 22, "42": 23,
      "43": 24, "44": 25, "45": 26, "46": 27, "47": 28, "48": 28, "49": 29, "5": 3, "50": 30, "51": 31, "52": 31,
      "53": 32, "54": 33, "55": 33, "56": 33, "57": 34, "58": 34, "59": 35, "6": 3, "60": 36, "61": 37, "62": 38,
      "63": 39, "64": 40, "65": 40, "66": 41, "67": 42, "68": 43, "69": 44, "7": 4, "70": 44, "71": 45, "72": 46,
      "73": 46, "74": 47, "75": 48, "76": 49, "77": 50, "78": 51, "79": 52, "8": 4, "80": 53, "81": 54, "82": 55,
      "83": 56, "84": 56, "85": 56, "86": 56, "87": 57, "88": 58, "89": 58, "9": 5, "90": 59, "91": 60, "92": 61,
      "93": 61, "94": 62, "95": 62, "96": 62, "97": 63, "98": 64, "99": 64},
 "usage_RelationAsSet_Explicit_2":
     {"1": 4, "10": 6, "100": 2, "101": 4, "102": 4, "103": 2, "104": 4, "105": 6, "106": 6, "107": 6, "108": 5,
      "109": 2, "11": 4, "110": 1, "111": 2, "112": 4, "113": 6, "114": 2, "115": 6, "116": 2, "117": 4, "118": 2,
      "119": 1, "12": 5, "120": 4, "121": 4, "122": 5, "123": 2, "124": 3, "125": 1, "126": 2, "127": 4, "128": 5,
      "129": 4, "13": 5, "130": 2, "131": 4, "132": 5, "133": 6, "134": 2, "135": 4, "136": 2, "137": 3, "138": 5,
      "139": 4, "14": 3, "140": 4, "141": 6, "142": 6, "143": 6, "144": 4, "145": 5, "146": 1, "147": 4, "148": 1,
      "149": 6, "15": 4, "150": 1, "151": 4, "152": 2, "153": 2, "154": 4, "155": 5, "16": 5, "17": 5, "18": 6, "19": 4,
      "2": 6, "20": 5, "21": 4, "22": 5, "23": 6, "24": 3, "25": 5, "26": 3, "27": 1, "28": 2, "29": 6, "3": 1, "30": 2,
      "31": 5, "32": 1, "33": 2, "34": 4, "35": 5, "36": 3, "37": 4, "38": 5, "39": 6, "4": 3, "40": 3, "41": 5,
      "42": 3, "43": 4, "44": 2, "45": 6, "46": 1, "47": 2, "48": 6, "49": 6, "5": 4, "50": 2, "51": 1, "52": 5,
      "53": 5, "54": 1, "55": 2, "56": 4, "57": 1, "58": 6, "59": 1, "6": 5, "60": 6, "61": 2, "62": 6, "63": 6,
      "64": 5, "65": 6, "66": 6, "67": 6, "68": 4, "69": 3, "7": 3, "70": 5, "71": 6, "72": 1, "73": 5, "74": 4,
      "75": 3, "76": 3, "77": 6, "78": 6, "79": 1, "8": 5, "80": 6, "81": 5, "82": 6, "83": 1, "84": 2, "85": 3,
      "86": 5, "87": 1, "88": 4, "89": 5, "9": 5, "90": 4, "91": 1, "92": 1, "93": 4, "94": 3, "95": 4, "96": 6,
      "97": 6, "98": 2, "99": 4}}