{"costTC_FunctionND":
     {"1": {"1": 1, "2": 4, "3": 2, "4": 9, "5": 1}, "10": {"1": 7, "2": 5, "3": 2, "4": 7, "5": 4},
      "11": {"1": 3, "2": 8, "3": 4, "4": 7, "5": 5}, "12": {"1": 9, "2": 7, "3": 2, "4": 7, "5": 10},
      "13": {"1": 10, "2": 10, "3": 6, "4": 1, "5": 2}, "14": {"1": 5, "2": 8, "3": 9, "4": 8, "5": 6},
      "15": {"1": 7, "2": 9, "3": 10, "4": 3, "5": 9}, "16": {"1": 8, "2": 8, "3": 3, "4": 7, "5": 10},
      "17": {"1": 5, "2": 2, "3": 6, "4": 3, "5": 1}, "18": {"1": 5, "2": 6, "3": 8, "4": 7, "5": 4},
      "19": {"1": 4, "2": 2, "3": 3, "4": 7, "5": 3}, "2": {"1": 3, "2": 3, "3": 9, "4": 5, "5": 2},
      "20": {"1": 3, "2": 8, "3": 3, "4": 8, "5": 2}, "3": {"1": 9, "2": 7, "3": 6, "4": 9, "5": 4},
      "4": {"1": 5, "2": 5, "3": 6, "4": 5, "5": 1}, "5": {"1": 8, "2": 5, "3": 8, "4": 9, "5": 6},
      "6": {"1": 6, "2": 6, "3": 6, "4": 5, "5": 10}, "7": {"1": 1, "2": 6, "3": 6, "4": 10, "5": 5},
      "8": {"1": 10, "2": 8, "3": 8, "4": 2, "5": 9}, "9": {"1": 6, "2": 3, "3": 10, "4": 9, "5": 6}},
 "costWT_FunctionND":
     {"1":
          {"1": 1, "10": 2, "11": 2, "12": 1, "13": 3, "14": 2, "15": 3, "16": 2, "17": 1, "18": 2, "19": 3, "2": 3,
           "20": 3, "3": 2, "4": 3, "5": 2, "6": 3, "7": 2, "8": 3, "9": 1},
      "10":
          {"1": 2, "10": 2, "11": 1, "12": 2, "13": 1, "14": 3, "15": 2, "16": 3, "17": 1, "18": 1, "19": 1, "2": 1,
           "20": 2, "3": 2, "4": 1, "5": 3, "6": 1, "7": 2, "8": 3, "9": 1},
      "11":
          {"1": 3, "10": 2, "11": 2, "12": 3, "13": 3, "14": 1, "15": 3, "16": 1, "17": 3, "18": 2, "19": 2, "2": 1,
           "20": 1, "3": 2, "4": 1, "5": 3, "6": 3, "7": 2, "8": 2, "9": 3},
      "12":
          {"1": 2, "10": 2, "11": 1, "12": 1, "13": 1, "14": 1, "15": 1, "16": 2, "17": 1, "18": 2, "19": 2, "2": 2,
           "20": 2, "3": 3, "4": 3, "5": 3, "6": 3, "7": 3, "8": 1, "9": 2},
      "13":
          {"1": 2, "10": 3, "11": 3, "12": 1, "13": 2, "14": 3, "15": 1, "16": 2, "17": 3, "18": 1, "19": 1, "2": 3,
           "20": 2, "3": 3, "4": 2, "5": 3, "6": 2, "7": 1, "8": 3, "9": 2},
      "14":
          {"1": 3, "10": 1, "11": 3, "12": 2, "13": 1, "14": 2, "15": 2, "16": 1, "17": 2, "18": 1, "19": 2, "2": 1,
           "20": 1, "3": 3, "4": 3, "5": 1, "6": 1, "7": 3, "8": 1, "9": 2},
      "15":
          {"1": 2, "10": 2, "11": 3, "12": 1, "13": 3, "14": 3, "15": 2, "16": 1, "17": 3, "18": 2, "19": 3, "2": 1,
           "20": 1, "3": 3, "4": 2, "5": 3, "6": 3, "7": 1, "8": 1, "9": 1},
      "16":
          {"1": 3, "10": 2, "11": 1, "12": 3, "13": 3, "14": 1, "15": 2, "16": 3, "17": 3, "18": 3, "19": 1, "2": 1,
           "20": 3, "3": 1, "4": 2, "5": 3, "6": 1, "7": 3, "8": 3, "9": 2},
      "17":
          {"1": 3, "10": 3, "11": 1, "12": 1, "13": 1, "14": 1, "15": 1, "16": 3, "17": 1, "18": 3, "19": 3, "2": 2,
           "20": 2, "3": 3, "4": 2, "5": 2, "6": 1, "7": 3, "8": 2, "9": 1},
      "18":
          {"1": 1, "10": 3, "11": 2, "12": 2, "13": 3, "14": 1, "15": 2, "16": 3, "17": 2, "18": 1, "19": 3, "2": 3,
           "20": 1, "3": 1, "4": 3, "5": 2, "6": 3, "7": 1, "8": 3, "9": 3},
      "19":
          {"1": 1, "10": 1, "11": 1, "12": 3, "13": 1, "14": 3, "15": 2, "16": 2, "17": 3, "18": 1, "19": 1, "2": 2,
           "20": 2, "3": 1, "4": 3, "5": 1, "6": 3, "7": 2, "8": 3, "9": 2},
      "2":
          {"1": 2, "10": 2, "11": 3, "12": 2, "13": 3, "14": 2, "15": 1, "16": 2, "17": 3, "18": 3, "19": 3, "2": 1,
           "20": 2, "3": 2, "4": 3, "5": 2, "6": 1, "7": 3, "8": 3, "9": 2},
      "20":
          {"1": 2, "10": 2, "11": 3, "12": 1, "13": 1, "14": 3, "15": 3, "16": 1, "17": 3, "18": 3, "19": 1, "2": 2,
           "20": 2, "3": 2, "4": 3, "5": 3, "6": 1, "7": 3, "8": 2, "9": 2},
      "21":
          {"1": 1, "10": 1, "11": 1, "12": 3, "13": 1, "14": 2, "15": 1, "16": 3, "17": 1, "18": 1, "19": 2, "2": 1,
           "20": 1, "3": 3, "4": 3, "5": 1, "6": 1, "7": 2, "8": 2, "9": 1},
      "22":
          {"1": 1, "10": 2, "11": 2, "12": 3, "13": 3, "14": 3, "15": 3, "16": 3, "17": 1, "18": 3, "19": 2, "2": 1,
           "20": 3, "3": 1, "4": 2, "5": 2, "6": 2, "7": 2, "8": 2, "9": 3},
      "23":
          {"1": 1, "10": 2, "11": 3, "12": 3, "13": 3, "14": 1, "15": 1, "16": 1, "17": 1, "18": 3, "19": 3, "2": 1,
           "20": 2, "3": 1, "4": 1, "5": 2, "6": 2, "7": 3, "8": 3, "9": 2},
      "24":
          {"1": 3, "10": 1, "11": 1, "12": 3, "13": 2, "14": 2, "15": 3, "16": 3, "17": 3, "18": 3, "19": 1, "2": 1,
           "20": 1, "3": 1, "4": 1, "5": 3, "6": 1, "7": 3, "8": 2, "9": 2},
      "25":
          {"1": 2, "10": 1, "11": 3, "12": 2, "13": 1, "14": 2, "15": 2, "16": 2, "17": 2, "18": 1, "19": 2, "2": 1,
           "20": 1, "3": 2, "4": 3, "5": 3, "6": 3, "7": 1, "8": 2, "9": 1},
      "26":
          {"1": 1, "10": 2, "11": 3, "12": 1, "13": 2, "14": 3, "15": 1, "16": 1, "17": 1, "18": 1, "19": 3, "2": 3,
           "20": 2, "3": 1, "4": 3, "5": 1, "6": 1, "7": 2, "8": 1, "9": 1},
      "27":
          {"1": 2, "10": 1, "11": 1, "12": 1, "13": 2, "14": 1, "15": 3, "16": 1, "17": 1, "18": 3, "19": 1, "2": 1,
           "20": 3, "3": 1, "4": 2, "5": 1, "6": 2, "7": 1, "8": 3, "9": 1},
      "28":
          {"1": 3, "10": 1, "11": 1, "12": 1, "13": 3, "14": 1, "15": 3, "16": 2, "17": 1, "18": 1, "19": 3, "2": 1,
           "20": 2, "3": 1, "4": 2, "5": 3, "6": 2, "7": 1, "8": 3, "9": 2},
      "29":
          {"1": 3, "10": 2, "11": 2, "12": 1, "13": 3, "14": 1, "15": 2, "16": 1, "17": 3, "18": 3, "19": 3, "2": 1,
           "20": 2, "3": 2, "4": 2, "5": 3, "6": 2, "7": 3, "8": 2, "9": 3},
      "3":
          {"1": 1, "10": 3, "11": 2, "12": 2, "13": 3, "14": 3, "15": 2, "16": 1, "17": 1, "18": 3, "19": 3, "2": 1,
           "20": 1, "3": 2, "4": 2, "5": 2, "6": 1, "7": 3, "8": 1, "9": 3},
      "30":
          {"1": 2, "10": 3, "11": 1, "12": 1, "13": 1, "14": 3, "15": 3, "16": 2, "17": 2, "18": 2, "19": 2, "2": 2,
           "20": 2, "3": 1, "4": 3, "5": 1, "6": 2, "7": 1, "8": 2, "9": 2},
      "31":
          {"1": 3, "10": 2, "11": 2, "12": 2, "13": 3, "14": 1, "15": 2, "16": 2, "17": 3, "18": 1, "19": 1, "2": 3,
           "20": 2, "3": 3, "4": 1, "5": 2, "6": 1, "7": 2, "8": 1, "9": 2},
      "32":
          {"1": 1, "10": 2, "11": 3, "12": 2, "13": 3, "14": 2, "15": 1, "16": 2, "17": 2, "18": 1, "19": 1, "2": 1,
           "20": 3, "3": 1, "4": 3, "5": 1, "6": 3, "7": 2, "8": 2, "9": 2},
      "33":
          {"1": 2, "10": 1, "11": 3, "12": 3, "13": 1, "14": 3, "15": 3, "16": 3, "17": 2, "18": 2, "19": 3, "2": 3,
           "20": 2, "3": 1, "4": 1, "5": 2, "6": 1, "7": 2, "8": 2, "9": 3},
      "34":
          {"1": 1, "10": 2, "11": 3, "12": 2, "13": 2, "14": 2, "15": 2, "16": 1, "17": 1, "18": 3, "19": 3, "2": 3,
           "20": 1, "3": 1, "4": 1, "5": 3, "6": 3, "7": 2, "8": 3, "9": 2},
      "35":
          {"1": 3, "10": 3, "11": 1, "12": 2, "13": 3, "14": 3, "15": 3, "16": 2, "17": 3, "18": 1, "19": 3, "2": 1,
           "20": 1, "3": 1, "4": 3, "5": 1, "6": 1, "7": 2, "8": 3, "9": 3},
      "36":
          {"1": 3, "10": 1, "11": 2, "12": 3, "13": 2, "14": 1, "15": 3, "16": 3, "17": 3, "18": 2, "19": 3, "2": 3,
           "20": 3, "3": 3, "4": 2, "5": 1, "6": 2, "7": 3, "8": 1, "9": 3},
      "4":
          {"1": 3, "10": 1, "11": 3, "12": 1, "13": 3, "14": 2, "15": 3, "16": 3, "17": 2, "18": 1, "19": 1, "2": 1,
           "20": 2, "3": 1, "4": 2, "5": 2, "6": 3, "7": 2, "8": 3, "9": 1},
      "5":
          {"1": 3, "10": 3, "11": 2, "12": 1, "13": 1, "14": 3, "15": 1, "16": 2, "17": 1, "18": 3, "19": 1, "2": 3,
           "20": 3, "3": 1, "4": 1, "5": 1, "6": 2, "7": 3, "8": 2, "9": 2},
      "6":
          {"1": 2, "10": 3, "11": 1, "12": 1, "13": 3, "14": 2, "15": 2, "16": 2, "17": 2, "18": 3, "19": 3, "2": 3,
           "20": 2, "3": 2, "4": 1, "5": 3, "6": 1, "7": 3, "8": 2, "9": 2},
      "7":
          {"1": 2, "10": 2, "11": 2, "12": 2, "13": 1, "14": 1, "15": 2, "16": 2, "17": 1, "18": 1, "19": 2, "2": 1,
           "20": 2, "3": 3, "4": 1, "5": 3, "6": 1, "7": 3, "8": 1, "9": 3},
      "8":
          {"1": 1, "10": 1, "11": 2, "12": 2, "13": 2, "14": 2, "15": 3, "16": 2, "17": 3, "18": 2, "19": 3, "2": 3,
           "20": 3, "3": 2, "4": 1, "5": 1, "6": 1, "7": 2, "8": 1, "9": 3},
      "9":
          {"1": 2, "10": 2, "11": 1, "12": 2, "13": 3, "14": 1, "15": 1, "16": 2, "17": 2, "18": 1, "19": 1, "2": 1,
           "20": 3, "3": 2, "4": 1, "5": 2, "6": 1, "7": 2, "8": 1, "9": 1}},
 "demand_Function1D": {"1": 19, "2": 18, "3": 18, "4": 17, "5": 18}, "fin1": 720, "fin2": 3, "fin3": 100, "fin4": 10,
 "fin5": 36, "fin6": 6, "fin7": 5, "fin8": 19, "maxCost": 47, "n_customer": 5, "n_transshipment": 20,
 "n_warehouses": 36,
 "stock_Function1D":
     {"1": 2, "10": 3, "11": 1, "12": 4, "13": 5, "14": 1, "15": 6, "16": 2, "17": 5, "18": 2, "19": 6, "2": 4, "20": 1,
      "21": 4, "22": 5, "23": 6, "24": 1, "25": 2, "26": 6, "27": 5, "28": 3, "29": 1, "3": 4, "30": 5, "31": 4,
      "32": 2, "33": 6, "34": 3, "35": 1, "36": 5, "4": 1, "5": 4, "6": 4, "7": 4, "8": 1, "9": 5}}