{"costTC_FunctionND":
     {"1": {"1": 2, "2": 9, "3": 9, "4": 4}, "10": {"1": 2, "2": 8, "3": 2, "4": 7},
      "11": {"1": 4, "2": 5, "3": 6, "4": 4}, "12": {"1": 10, "2": 4, "3": 7, "4": 6},
      "13": {"1": 8, "2": 3, "3": 2, "4": 2}, "14": {"1": 9, "2": 1, "3": 4, "4": 2},
      "15": {"1": 2, "2": 9, "3": 3, "4": 8}, "16": {"1": 5, "2": 10, "3": 9, "4": 10},
      "17": {"1": 2, "2": 1, "3": 3, "4": 7}, "18": {"1": 1, "2": 1, "3": 1, "4": 4},
      "19": {"1": 9, "2": 9, "3": 3, "4": 4}, "2": {"1": 5, "2": 9, "3": 1, "4": 5},
      "20": {"1": 6, "2": 5, "3": 5, "4": 8}, "21": {"1": 2, "2": 5, "3": 8, "4": 3},
      "22": {"1": 4, "2": 2, "3": 3, "4": 7}, "23": {"1": 6, "2": 7, "3": 2, "4": 1},
      "24": {"1": 4, "2": 3, "3": 3, "4": 7}, "25": {"1": 5, "2": 1, "3": 9, "4": 7},
      "26": {"1": 4, "2": 9, "3": 1, "4": 4}, "27": {"1": 10, "2": 9, "3": 8, "4": 9},
      "28": {"1": 6, "2": 5, "3": 5, "4": 6}, "29": {"1": 4, "2": 4, "3": 1, "4": 6},
      "3": {"1": 2, "2": 2, "3": 10, "4": 3}, "30": {"1": 8, "2": 3, "3": 5, "4": 8},
      "31": {"1": 6, "2": 8, "3": 6, "4": 9}, "32": {"1": 6, "2": 1, "3": 5, "4": 3},
      "33": {"1": 8, "2": 7, "3": 3, "4": 6}, "34": {"1": 7, "2": 4, "3": 9, "4": 8},
      "4": {"1": 10, "2": 4, "3": 2, "4": 9}, "5": {"1": 10, "2": 4, "3": 1, "4": 5},
      "6": {"1": 10, "2": 7, "3": 1, "4": 10}, "7": {"1": 5, "2": 1, "3": 6, "4": 8},
      "8": {"1": 1, "2": 9, "3": 5, "4": 9}, "9": {"1": 4, "2": 7, "3": 2, "4": 4}},
 "costWT_FunctionND":
     {"1":
          {"1": 2, "10": 2, "11": 2, "12": 2, "13": 2, "14": 2, "15": 2, "16": 2, "17": 2, "18": 2, "19": 2, "2": 2,
           "20": 2, "21": 2, "22": 2, "23": 2, "24": 2, "25": 2, "26": 2, "27": 2, "28": 2, "29": 2, "3": 2, "30": 2,
           "31": 2, "32": 2, "33": 2, "34": 2, "4": 2, "5": 2, "6": 2, "7": 2, "8": 2, "9": 2},
      "10":
          {"1": 2, "10": 2, "11": 2, "12": 2, "13": 2, "14": 2, "15": 2, "16": 2, "17": 2, "18": 2, "19": 2, "2": 2,
           "20": 2, "21": 2, "22": 2, "23": 2, "24": 2, "25": 2, "26": 2, "27": 2, "28": 2, "29": 2, "3": 2, "30": 2,
           "31": 2, "32": 2, "33": 2, "34": 2, "4": 2, "5": 2, "6": 2, "7": 2, "8": 2, "9": 2},
      "11":
          {"1": 2, "10": 2, "11": 2, "12": 2, "13": 2, "14": 2, "15": 2, "16": 2, "17": 2, "18": 2, "19": 2, "2": 2,
           "20": 2, "21": 2, "22": 2, "23": 2, "24": 2, "25": 2, "26": 2, "27": 2, "28": 2, "29": 2, "3": 2, "30": 2,
           "31": 2, "32": 2, "33": 2, "34": 2, "4": 2, "5": 2, "6": 2, "7": 2, "8": 2, "9": 2},
      "12":
          {"1": 2, "10": 2, "11": 2, "12": 2, "13": 2, "14": 2, "15": 2, "16": 2, "17": 2, "18": 2, "19": 2, "2": 2,
           "20": 2, "21": 2, "22": 2, "23": 2, "24": 2, "25": 2, "26": 2, "27": 2, "28": 2, "29": 2, "3": 2, "30": 2,
           "31": 2, "32": 2, "33": 2, "34": 2, "4": 2, "5": 2, "6": 2, "7": 2, "8": 2, "9": 2},
      "13":
          {"1": 2, "10": 2, "11": 2, "12": 2, "13": 2, "14": 2, "15": 2, "16": 2, "17": 2, "18": 2, "19": 2, "2": 2,
           "20": 2, "21": 2, "22": 2, "23": 2, "24": 2, "25": 2, "26": 2, "27": 2, "28": 2, "29": 2, "3": 2, "30": 2,
           "31": 2, "32": 2, "33": 2, "34": 2, "4": 2, "5": 2, "6": 2, "7": 2, "8": 2, "9": 2},
      "14":
          {"1": 2, "10": 2, "11": 2, "12": 2, "13": 2, "14": 2, "15": 2, "16": 2, "17": 2, "18": 2, "19": 2, "2": 2,
           "20": 2, "21": 2, "22": 2, "23": 2, "24": 2, "25": 2, "26": 2, "27": 2, "28": 2, "29": 2, "3": 2, "30": 2,
           "31": 2, "32": 2, "33": 2, "34": 2, "4": 2, "5": 2, "6": 2, "7": 2, "8": 2, "9": 2},
      "15":
          {"1": 2, "10": 2, "11": 2, "12": 2, "13": 2, "14": 2, "15": 2, "16": 2, "17": 2, "18": 2, "19": 2, "2": 2,
           "20": 2, "21": 2, "22": 2, "23": 2, "24": 2, "25": 2, "26": 2, "27": 2, "28": 2, "29": 2, "3": 2, "30": 2,
           "31": 2, "32": 2, "33": 2, "34": 2, "4": 2, "5": 2, "6": 2, "7": 2, "8": 2, "9": 2},
      "16":
          {"1": 2, "10": 2, "11": 2, "12": 2, "13": 2, "14": 2, "15": 2, "16": 2, "17": 2, "18": 2, "19": 2, "2": 2,
           "20": 2, "21": 2, "22": 2, "23": 2, "24": 2, "25": 2, "26": 2, "27": 2, "28": 2, "29": 2, "3": 2, "30": 2,
           "31": 2, "32": 2, "33": 2, "34": 2, "4": 2, "5": 2, "6": 2, "7": 2, "8": 2, "9": 2},
      "17":
          {"1": 2, "10": 2, "11": 2, "12": 2, "13": 2, "14": 2, "15": 2, "16": 2, "17": 2, "18": 2, "19": 2, "2": 2,
           "20": 2, "21": 2, "22": 2, "23": 2, "24": 2, "25": 2, "26": 2, "27": 2, "28": 2, "29": 2, "3": 2, "30": 2,
           "31": 2, "32": 2, "33": 2, "34": 2, "4": 2, "5": 2, "6": 2, "7": 2, "8": 2, "9": 2},
      "18":
          {"1": 2, "10": 2, "11": 2, "12": 2, "13": 2, "14": 2, "15": 2, "16": 2, "17": 2, "18": 2, "19": 2, "2": 2,
           "20": 2, "21": 2, "22": 2, "23": 2, "24": 2, "25": 2, "26": 2, "27": 2, "28": 2, "29": 2, "3": 2, "30": 2,
           "31": 2, "32": 2, "33": 2, "34": 2, "4": 2, "5": 2, "6": 2, "7": 2, "8": 2, "9": 2},
      "19":
          {"1": 2, "10": 2, "11": 2, "12": 2, "13": 2, "14": 2, "15": 2, "16": 2, "17": 2, "18": 2, "19": 2, "2": 2,
           "20": 2, "21": 2, "22": 2, "23": 2, "24": 2, "25": 2, "26": 2, "27": 2, "28": 2, "29": 2, "3": 2, "30": 2,
           "31": 2, "32": 2, "33": 2, "34": 2, "4": 2, "5": 2, "6": 2, "7": 2, "8": 2, "9": 2},
      "2":
          {"1": 2, "10": 2, "11": 2, "12": 2, "13": 2, "14": 2, "15": 2, "16": 2, "17": 2, "18": 2, "19": 2, "2": 2,
           "20": 2, "21": 2, "22": 2, "23": 2, "24": 2, "25": 2, "26": 2, "27": 2, "28": 2, "29": 2, "3": 2, "30": 2,
           "31": 2, "32": 2, "33": 2, "34": 2, "4": 2, "5": 2, "6": 2, "7": 2, "8": 2, "9": 2},
      "20":
          {"1": 2, "10": 2, "11": 2, "12": 2, "13": 2, "14": 2, "15": 2, "16": 2, "17": 2, "18": 2, "19": 2, "2": 2,
           "20": 2, "21": 2, "22": 2, "23": 2, "24": 2, "25": 2, "26": 2, "27": 2, "28": 2, "29": 2, "3": 2, "30": 2,
           "31": 2, "32": 2, "33": 2, "34": 2, "4": 2, "5": 2, "6": 2, "7": 2, "8": 2, "9": 2},
      "21":
          {"1": 2, "10": 2, "11": 2, "12": 2, "13": 2, "14": 2, "15": 2, "16": 2, "17": 2, "18": 2, "19": 2, "2": 2,
           "20": 2, "21": 2, "22": 2, "23": 2, "24": 2, "25": 2, "26": 2, "27": 2, "28": 2, "29": 2, "3": 2, "30": 2,
           "31": 2, "32": 2, "33": 2, "34": 2, "4": 2, "5": 2, "6": 2, "7": 2, "8": 2, "9": 2},
      "22":
          {"1": 2, "10": 2, "11": 2, "12": 2, "13": 2, "14": 2, "15": 2, "16": 2, "17": 2, "18": 2, "19": 2, "2": 2,
           "20": 2, "21": 2, "22": 2, "23": 2, "24": 2, "25": 2, "26": 2, "27": 2, "28": 2, "29": 2, "3": 2, "30": 2,
           "31": 2, "32": 2, "33": 2, "34": 2, "4": 2, "5": 2, "6": 2, "7": 2, "8": 2, "9": 2},
      "23":
          {"1": 2, "10": 2, "11": 2, "12": 2, "13": 2, "14": 2, "15": 2, "16": 2, "17": 2, "18": 2, "19": 2, "2": 2,
           "20": 2, "21": 2, "22": 2, "23": 2, "24": 2, "25": 2, "26": 2, "27": 2, "28": 2, "29": 2, "3": 2, "30": 2,
           "31": 2, "32": 2, "33": 2, "34": 2, "4": 2, "5": 2, "6": 2, "7": 2, "8": 2, "9": 2},
      "24":
          {"1": 2, "10": 2, "11": 2, "12": 2, "13": 2, "14": 2, "15": 2, "16": 2, "17": 2, "18": 2, "19": 2, "2": 2,
           "20": 2, "21": 2, "22": 2, "23": 2, "24": 2, "25": 2, "26": 2, "27": 2, "28": 2, "29": 2, "3": 2, "30": 2,
           "31": 2, "32": 2, "33": 2, "34": 2, "4": 2, "5": 2, "6": 2, "7": 2, "8": 2, "9": 2},
      "25":
          {"1": 2, "10": 2, "11": 2, "12": 2, "13": 2, "14": 2, "15": 2, "16": 2, "17": 2, "18": 2, "19": 2, "2": 2,
           "20": 2, "21": 2, "22": 2, "23": 2, "24": 2, "25": 2, "26": 2, "27": 2, "28": 2, "29": 2, "3": 2, "30": 2,
           "31": 2, "32": 2, "33": 2, "34": 2, "4": 2, "5": 2, "6": 2, "7": 2, "8": 2, "9": 2},
      "26":
          {"1": 2, "10": 2, "11": 2, "12": 2, "13": 2, "14": 2, "15": 2, "16": 2, "17": 2, "18": 2, "19": 2, "2": 2,
           "20": 2, "21": 2, "22": 2, "23": 2, "24": 2, "25": 2, "26": 2, "27": 2, "28": 2, "29": 2, "3": 2, "30": 2,
           "31": 2, "32": 2, "33": 2, "34": 2, "4": 2, "5": 2, "6": 2, "7": 2, "8": 2, "9": 2},
      "27":
          {"1": 2, "10": 2, "11": 2, "12": 2, "13": 2, "14": 2, "15": 2, "16": 2, "17": 2, "18": 2, "19": 2, "2": 2,
           "20": 2, "21": 2, "22": 2, "23": 2, "24": 2, "25": 2, "26": 2, "27": 2, "28": 2, "29": 2, "3": 2, "30": 2,
           "31": 2, "32": 2, "33": 2, "34": 2, "4": 2, "5": 2, "6": 2, "7": 2, "8": 2, "9": 2},
      "28":
          {"1": 2, "10": 2, "11": 2, "12": 2, "13": 2, "14": 2, "15": 2, "16": 2, "17": 2, "18": 2, "19": 2, "2": 2,
           "20": 2, "21": 2, "22": 2, "23": 2, "24": 2, "25": 2, "26": 2, "27": 2, "28": 2, "29": 2, "3": 2, "30": 2,
           "31": 2, "32": 2, "33": 2, "34": 2, "4": 2, "5": 2, "6": 2, "7": 2, "8": 2, "9": 2},
      "29":
          {"1": 2, "10": 2, "11": 2, "12": 2, "13": 2, "14": 2, "15": 2, "16": 2, "17": 2, "18": 2, "19": 2, "2": 2,
           "20": 2, "21": 2, "22": 2, "23": 2, "24": 2, "25": 2, "26": 2, "27": 2, "28": 2, "29": 2, "3": 2, "30": 2,
           "31": 2, "32": 2, "33": 2, "34": 2, "4": 2, "5": 2, "6": 2, "7": 2, "8": 2, "9": 2},
      "3":
          {"1": 2, "10": 2, "11": 2, "12": 2, "13": 2, "14": 2, "15": 2, "16": 2, "17": 2, "18": 2, "19": 2, "2": 2,
           "20": 2, "21": 2, "22": 2, "23": 2, "24": 2, "25": 2, "26": 2, "27": 2, "28": 2, "29": 2, "3": 2, "30": 2,
           "31": 2, "32": 2, "33": 2, "34": 2, "4": 2, "5": 2, "6": 2, "7": 2, "8": 2, "9": 2},
      "30":
          {"1": 2, "10": 2, "11": 2, "12": 2, "13": 2, "14": 2, "15": 2, "16": 2, "17": 2, "18": 2, "19": 2, "2": 2,
           "20": 2, "21": 2, "22": 2, "23": 2, "24": 2, "25": 2, "26": 2, "27": 2, "28": 2, "29": 2, "3": 2, "30": 2,
           "31": 2, "32": 2, "33": 2, "34": 2, "4": 2, "5": 2, "6": 2, "7": 2, "8": 2, "9": 2},
      "31":
          {"1": 2, "10": 2, "11": 2, "12": 2, "13": 2, "14": 2, "15": 2, "16": 2, "17": 2, "18": 2, "19": 2, "2": 2,
           "20": 2, "21": 2, "22": 2, "23": 2, "24": 2, "25": 2, "26": 2, "27": 2, "28": 2, "29": 2, "3": 2, "30": 2,
           "31": 2, "32": 2, "33": 2, "34": 2, "4": 2, "5": 2, "6": 2, "7": 2, "8": 2, "9": 2},
      "32":
          {"1": 2, "10": 2, "11": 2, "12": 2, "13": 2, "14": 2, "15": 2, "16": 2, "17": 2, "18": 2, "19": 2, "2": 2,
           "20": 2, "21": 2, "22": 2, "23": 2, "24": 2, "25": 2, "26": 2, "27": 2, "28": 2, "29": 2, "3": 2, "30": 2,
           "31": 2, "32": 2, "33": 2, "34": 2, "4": 2, "5": 2, "6": 2, "7": 2, "8": 2, "9": 2},
      "33":
          {"1": 2, "10": 2, "11": 2, "12": 2, "13": 2, "14": 2, "15": 2, "16": 2, "17": 2, "18": 2, "19": 2, "2": 2,
           "20": 2, "21": 2, "22": 2, "23": 2, "24": 2, "25": 2, "26": 2, "27": 2, "28": 2, "29": 2, "3": 2, "30": 2,
           "31": 2, "32": 2, "33": 2, "34": 2, "4": 2, "5": 2, "6": 2, "7": 2, "8": 2, "9": 2},
      "34":
          {"1": 2, "10": 2, "11": 2, "12": 2, "13": 2, "14": 2, "15": 2, "16": 2, "17": 2, "18": 2, "19": 2, "2": 2,
           "20": 2, "21": 2, "22": 2, "23": 2, "24": 2, "25": 2, "26": 2, "27": 2, "28": 2, "29": 2, "3": 2, "30": 2,
           "31": 2, "32": 2, "33": 2, "34": 2, "4": 2, "5": 2, "6": 2, "7": 2, "8": 2, "9": 2},
      "35":
          {"1": 2, "10": 2, "11": 2, "12": 2, "13": 2, "14": 2, "15": 2, "16": 2, "17": 2, "18": 2, "19": 2, "2": 2,
           "20": 2, "21": 2, "22": 2, "23": 2, "24": 2, "25": 2, "26": 2, "27": 2, "28": 2, "29": 2, "3": 2, "30": 2,
           "31": 2, "32": 2, "33": 2, "34": 2, "4": 2, "5": 2, "6": 2, "7": 2, "8": 2, "9": 2},
      "4":
          {"1": 2, "10": 2, "11": 2, "12": 2, "13": 2, "14": 2, "15": 2, "16": 2, "17": 2, "18": 2, "19": 2, "2": 2,
           "20": 2, "21": 2, "22": 2, "23": 2, "24": 2, "25": 2, "26": 2, "27": 2, "28": 2, "29": 2, "3": 2, "30": 2,
           "31": 2, "32": 2, "33": 2, "34": 2, "4": 2, "5": 2, "6": 2, "7": 2, "8": 2, "9": 2},
      "5":
          {"1": 2, "10": 2, "11": 2, "12": 2, "13": 2, "14": 2, "15": 2, "16": 2, "17": 2, "18": 2, "19": 2, "2": 2,
           "20": 2, "21": 2, "22": 2, "23": 2, "24": 2, "25": 2, "26": 2, "27": 2, "28": 2, "29": 2, "3": 2, "30": 2,
           "31": 2, "32": 2, "33": 2, "34": 2, "4": 2, "5": 2, "6": 2, "7": 2, "8": 2, "9": 2},
      "6":
          {"1": 2, "10": 2, "11": 2, "12": 2, "13": 2, "14": 2, "15": 2, "16": 2, "17": 2, "18": 2, "19": 2, "2": 2,
           "20": 2, "21": 2, "22": 2, "23": 2, "24": 2, "25": 2, "26": 2, "27": 2, "28": 2, "29": 2, "3": 2, "30": 2,
           "31": 2, "32": 2, "33": 2, "34": 2, "4": 2, "5": 2, "6": 2, "7": 2, "8": 2, "9": 2},
      "7":
          {"1": 2, "10": 2, "11": 2, "12": 2, "13": 2, "14": 2, "15": 2, "16": 2, "17": 2, "18": 2, "19": 2, "2": 2,
           "20": 2, "21": 2, "22": 2, "23": 2, "24": 2, "25": 2, "26": 2, "27": 2, "28": 2, "29": 2, "3": 2, "30": 2,
           "31": 2, "32": 2, "33": 2, "34": 2, "4": 2, "5": 2, "6": 2, "7": 2, "8": 2, "9": 2},
      "8":
          {"1": 2, "10": 2, "11": 2, "12": 2, "13": 2, "14": 2, "15": 2, "16": 2, "17": 2, "18": 2, "19": 2, "2": 2,
           "20": 2, "21": 2, "22": 2, "23": 2, "24": 2, "25": 2, "26": 2, "27": 2, "28": 2, "29": 2, "3": 2, "30": 2,
           "31": 2, "32": 2, "33": 2, "34": 2, "4": 2, "5": 2, "6": 2, "7": 2, "8": 2, "9": 2},
      "9":
          {"1": 2, "10": 2, "11": 2, "12": 2, "13": 2, "14": 2, "15": 2, "16": 2, "17": 2, "18": 2, "19": 2, "2": 2,
           "20": 2, "21": 2, "22": 2, "23": 2, "24": 2, "25": 2, "26": 2, "27": 2, "28": 2, "29": 2, "3": 2, "30": 2,
           "31": 2, "32": 2, "33": 2, "34": 2, "4": 2, "5": 2, "6": 2, "7": 2, "8": 2, "9": 2}},
 "demand_Function1D": {"1": 23, "2": 23, "3": 24, "4": 24}, "fin1": 1190, "fin2": 2, "fin3": 136, "fin4": 10,
 "fin5": 35, "fin6": 50, "fin7": 4, "fin8": 24, "maxCost": 16, "n_customer": 4, "n_transshipment": 34,
 "n_warehouses": 35,
 "stock_Function1D":
     {"1": 33, "10": 32, "11": 44, "12": 27, "13": 48, "14": 20, "15": 19, "16": 37, "17": 28, "18": 20, "19": 24,
      "2": 40, "20": 24, "21": 40, "22": 43, "23": 49, "24": 39, "25": 30, "26": 25, "27": 50, "28": 48, "29": 18,
      "3": 24, "30": 42, "31": 19, "32": 22, "33": 26, "34": 43, "35": 18, "4": 31, "5": 41, "6": 41, "7": 37, "8": 35,
      "9": 44}}