{"blksize_delta_Function1D": {"1": 7, "2": 7, "3": 7, "4": 7, "5": 7}, "fin1": 91, "fin2": 6, "fin3": 5, "fin4": 10,
 "fin5": 5, "fin6": 7, "fin7": 126, "maxcars_Function1D": {"1": 9, "2": 9, "3": 9, "4": 9, "5": 10}, "n_cars": 276,
 "n_classes": 91, "n_options": 5,
 "quantity_Function1D":
     {"1": 6, "10": 3, "11": 3, "12": 3, "13": 3, "14": 3, "15": 3, "16": 3, "17": 3, "18": 3, "19": 3, "2": 3, "20": 3,
      "21": 3, "22": 3, "23": 3, "24": 3, "25": 3, "26": 3, "27": 3, "28": 3, "29": 3, "3": 3, "30": 3, "31": 3,
      "32": 3, "33": 3, "34": 3, "35": 3, "36": 3, "37": 3, "38": 3, "39": 3, "4": 3, "40": 3, "41": 3, "42": 3,
      "43": 3, "44": 3, "45": 3, "46": 3, "47": 3, "48": 3, "49": 3, "5": 3, "50": 3, "51": 3, "52": 3, "53": 3,
      "54": 3, "55": 3, "56": 3, "57": 3, "58": 3, "59": 3, "6": 3, "60": 3, "61": 3, "62": 3, "63": 3, "64": 3,
      "65": 3, "66": 3, "67": 3, "68": 3, "69": 3, "7": 3, "70": 3, "71": 3, "72": 3, "73": 3, "74": 3, "75": 3,
      "76": 3, "77": 3, "78": 3, "79": 3, "8": 3, "80": 3, "81": 3, "82": 3, "83": 3, "84": 3, "85": 3, "86": 3,
      "87": 3, "88": 3, "89": 3, "9": 3, "90": 3, "91": 3},
 "usage_RelationAsSet_Explicit_1":
     {"1": 1, "10": 10, "100": 71, "101": 72, "102": 73, "103": 73, "104": 74, "105": 75, "106": 75, "107": 76,
      "108": 77, "109": 77, "11": 11, "110": 78, "111": 79, "112": 79, "113": 80, "114": 81, "115": 82, "116": 83,
      "117": 84, "118": 85, "119": 86, "12": 11, "120": 87, "121": 88, "122": 89, "123": 89, "124": 90, "125": 91,
      "126": 91, "13": 12, "14": 13, "15": 14, "16": 14, "17": 15, "18": 15, "19": 16, "2": 2, "20": 16, "21": 17,
      "22": 18, "23": 19, "24": 19, "25": 20, "26": 21, "27": 22, "28": 23, "29": 24, "3": 3, "30": 25, "31": 26,
      "32": 26, "33": 27, "34": 28, "35": 29, "36": 30, "37": 30, "38": 31, "39": 32, "4": 4, "40": 33, "41": 34,
      "42": 35, "43": 36, "44": 37, "45": 38, "46": 38, "47": 38, "48": 38, "49": 39, "5": 5, "50": 40, "51": 41,
      "52": 41, "53": 42, "54": 43, "55": 43, "56": 44, "57": 44, "58": 45, "59": 46, "6": 6, "60": 46, "61": 47,
      "62": 48, "63": 48, "64": 49, "65": 50, "66": 50, "67": 50, "68": 51, "69": 52, "7": 7, "70": 52, "71": 52,
      "72": 53, "73": 53, "74": 54, "75": 55, "76": 55, "77": 55, "78": 56, "79": 56, "8": 8, "80": 57, "81": 58,
      "82": 59, "83": 60, "84": 61, "85": 61, "86": 61, "87": 62, "88": 63, "89": 64, "9": 9, "90": 64, "91": 65,
      "92": 66, "93": 66, "94": 66, "95": 67, "96": 68, "97": 69, "98": 70, "99": 71},
 "usage_RelationAsSet_Explicit_2":
     {"1": 5, "10": 5, "100": 5, "101": 5, "102": 3, "103": 4, "104": 4, "105": 3, "106": 4, "107": 4, "108": 3,
      "109": 4, "11": 2, "110": 5, "111": 1, "112": 2, "113": 5, "114": 5, "115": 5, "116": 5, "117": 5, "118": 5,
      "119": 4, "12": 4, "120": 2, "121": 5, "122": 2, "123": 5, "124": 1, "125": 1, "126": 3, "13": 4, "14": 5,
      "15": 1, "16": 2, "17": 3, "18": 5, "19": 3, "2": 2, "20": 5, "21": 1, "22": 5, "23": 1, "24": 3, "25": 5,
      "26": 5, "27": 5, "28": 4, "29": 5, "3": 5, "30": 1, "31": 1, "32": 2, "33": 5, "34": 3, "35": 5, "36": 1,
      "37": 5, "38": 3, "39": 5, "4": 5, "40": 3, "41": 2, "42": 2, "43": 1, "44": 2, "45": 2, "46": 3, "47": 4,
      "48": 5, "49": 2, "5": 1, "50": 2, "51": 2, "52": 5, "53": 5, "54": 2, "55": 5, "56": 1, "57": 5, "58": 3,
      "59": 2, "6": 2, "60": 5, "61": 5, "62": 2, "63": 5, "64": 4, "65": 1, "66": 4, "67": 5, "68": 1, "69": 2, "7": 5,
      "70": 3, "71": 5, "72": 1, "73": 3, "74": 1, "75": 1, "76": 3, "77": 5, "78": 1, "79": 5, "8": 5, "80": 4,
      "81": 5, "82": 5, "83": 5, "84": 1, "85": 2, "86": 4, "87": 5, "88": 5, "89": 3, "9": 4, "90": 4, "91": 4,
      "92": 1, "93": 3, "94": 4, "95": 3, "96": 5, "97": 5, "98": 5, "99": 2}}