{"class_Function1D":
     {"1": 1, "10": 2, "11": 1, "12": 2, "13": 2, "14": 1, "15": 1, "16": 1, "17": 1, "18": 1, "19": 1, "2": 2, "20": 2,
      "21": 2, "22": 2, "3": 2, "4": 2, "5": 1, "6": 1, "7": 1, "8": 2, "9": 2},
 "deck_length": 69, "deck_width": 77, "fin1": 22, "fin2": 22, "fin3": 22, "fin4": 1, "fin5": 17,
 "length_Function1D":
     {"1": 1, "10": 1, "11": 1, "12": 1, "13": 1, "14": 1, "15": 1, "16": 1, "17": 1, "18": 1, "19": 1, "2": 39,
      "20": 1, "21": 23, "22": 56, "3": 1, "4": 1, "5": 1, "6": 1, "7": 1, "8": 1, "9": 1},
 "n_classes": 2, "n_containers": 22,
 "separation_FunctionAsRelationR3_RelationAsSetR3_ExplicitR3_1_Explicit": {"1": {"1": 1, "2": 2}},
 "separation_FunctionAsRelationR3_RelationAsSetR3_ExplicitR3_2": {"1": 17},
 "width_Function1D":
     {"1": 1, "10": 15, "11": 1, "12": 5, "13": 1, "14": 1, "15": 1, "16": 1, "17": 3, "18": 1, "19": 1, "2": 14,
      "20": 1, "21": 6, "22": 5, "3": 7, "4": 1, "5": 1, "6": 1, "7": 1, "8": 1, "9": 1}}