{"costTC_FunctionND":
     {"1": {"1": 3, "2": 3, "3": 3, "4": 3, "5": 3, "6": 3}, "10": {"1": 3, "2": 3, "3": 3, "4": 3, "5": 3, "6": 3},
      "11": {"1": 3, "2": 3, "3": 3, "4": 3, "5": 3, "6": 3}, "12": {"1": 3, "2": 3, "3": 3, "4": 3, "5": 3, "6": 3},
      "13": {"1": 3, "2": 3, "3": 3, "4": 3, "5": 3, "6": 3}, "14": {"1": 3, "2": 3, "3": 3, "4": 3, "5": 3, "6": 3},
      "15": {"1": 3, "2": 3, "3": 3, "4": 3, "5": 3, "6": 3}, "16": {"1": 3, "2": 3, "3": 3, "4": 3, "5": 3, "6": 3},
      "17": {"1": 3, "2": 3, "3": 3, "4": 3, "5": 3, "6": 3}, "18": {"1": 3, "2": 3, "3": 3, "4": 3, "5": 3, "6": 3},
      "19": {"1": 3, "2": 3, "3": 3, "4": 3, "5": 3, "6": 3}, "2": {"1": 3, "2": 3, "3": 3, "4": 3, "5": 3, "6": 3},
      "20": {"1": 3, "2": 3, "3": 3, "4": 3, "5": 3, "6": 3}, "21": {"1": 3, "2": 3, "3": 3, "4": 3, "5": 3, "6": 3},
      "3": {"1": 3, "2": 3, "3": 3, "4": 3, "5": 3, "6": 3}, "4": {"1": 3, "2": 3, "3": 3, "4": 3, "5": 3, "6": 3},
      "5": {"1": 3, "2": 3, "3": 3, "4": 3, "5": 3, "6": 3}, "6": {"1": 3, "2": 3, "3": 3, "4": 3, "5": 3, "6": 3},
      "7": {"1": 3, "2": 3, "3": 3, "4": 3, "5": 3, "6": 3}, "8": {"1": 3, "2": 3, "3": 3, "4": 3, "5": 3, "6": 3},
      "9": {"1": 3, "2": 3, "3": 3, "4": 3, "5": 3, "6": 3}},
 "costWT_FunctionND":
     {"1":
          {"1": 3, "10": 2, "11": 2, "12": 3, "13": 2, "14": 3, "15": 2, "16": 2, "17": 3, "18": 1, "19": 1, "2": 1,
           "20": 1, "21": 3, "3": 2, "4": 3, "5": 1, "6": 1, "7": 1, "8": 3, "9": 1},
      "10":
          {"1": 2, "10": 3, "11": 1, "12": 3, "13": 1, "14": 2, "15": 2, "16": 1, "17": 1, "18": 3, "19": 1, "2": 3,
           "20": 2, "21": 2, "3": 2, "4": 3, "5": 1, "6": 2, "7": 3, "8": 3, "9": 3},
      "11":
          {"1": 2, "10": 3, "11": 3, "12": 3, "13": 1, "14": 2, "15": 3, "16": 2, "17": 1, "18": 3, "19": 3, "2": 1,
           "20": 1, "21": 3, "3": 3, "4": 1, "5": 3, "6": 3, "7": 1, "8": 1, "9": 3},
      "12":
          {"1": 2, "10": 1, "11": 3, "12": 2, "13": 2, "14": 3, "15": 1, "16": 3, "17": 2, "18": 2, "19": 1, "2": 3,
           "20": 2, "21": 3, "3": 3, "4": 1, "5": 2, "6": 2, "7": 3, "8": 2, "9": 3},
      "13":
          {"1": 3, "10": 3, "11": 3, "12": 2, "13": 3, "14": 1, "15": 3, "16": 2, "17": 2, "18": 3, "19": 2, "2": 3,
           "20": 2, "21": 2, "3": 1, "4": 2, "5": 2, "6": 1, "7": 3, "8": 2, "9": 1},
      "14":
          {"1": 1, "10": 1, "11": 1, "12": 3, "13": 2, "14": 3, "15": 3, "16": 2, "17": 3, "18": 1, "19": 2, "2": 3,
           "20": 1, "21": 1, "3": 1, "4": 1, "5": 1, "6": 1, "7": 2, "8": 1, "9": 2},
      "15":
          {"1": 3, "10": 1, "11": 3, "12": 1, "13": 1, "14": 3, "15": 3, "16": 2, "17": 1, "18": 2, "19": 3, "2": 2,
           "20": 1, "21": 2, "3": 1, "4": 1, "5": 3, "6": 1, "7": 2, "8": 1, "9": 2},
      "16":
          {"1": 1, "10": 1, "11": 1, "12": 1, "13": 1, "14": 3, "15": 1, "16": 2, "17": 3, "18": 2, "19": 2, "2": 2,
           "20": 3, "21": 3, "3": 1, "4": 1, "5": 2, "6": 1, "7": 2, "8": 2, "9": 1},
      "17":
          {"1": 1, "10": 3, "11": 1, "12": 2, "13": 1, "14": 3, "15": 2, "16": 2, "17": 3, "18": 3, "19": 3, "2": 3,
           "20": 3, "21": 2, "3": 2, "4": 2, "5": 3, "6": 1, "7": 1, "8": 2, "9": 1},
      "18":
          {"1": 1, "10": 2, "11": 2, "12": 2, "13": 3, "14": 2, "15": 2, "16": 1, "17": 1, "18": 2, "19": 2, "2": 3,
           "20": 2, "21": 3, "3": 3, "4": 2, "5": 3, "6": 2, "7": 3, "8": 1, "9": 1},
      "19":
          {"1": 2, "10": 2, "11": 1, "12": 3, "13": 2, "14": 2, "15": 2, "16": 1, "17": 1, "18": 2, "19": 3, "2": 3,
           "20": 1, "21": 1, "3": 1, "4": 3, "5": 2, "6": 2, "7": 3, "8": 1, "9": 2},
      "2":
          {"1": 3, "10": 2, "11": 2, "12": 1, "13": 2, "14": 2, "15": 3, "16": 1, "17": 1, "18": 2, "19": 3, "2": 3,
           "20": 3, "21": 2, "3": 2, "4": 2, "5": 2, "6": 1, "7": 1, "8": 1, "9": 2},
      "20":
          {"1": 2, "10": 1, "11": 1, "12": 1, "13": 3, "14": 1, "15": 1, "16": 1, "17": 1, "18": 2, "19": 3, "2": 1,
           "20": 3, "21": 3, "3": 3, "4": 3, "5": 1, "6": 1, "7": 1, "8": 3, "9": 1},
      "21":
          {"1": 1, "10": 2, "11": 3, "12": 2, "13": 2, "14": 3, "15": 1, "16": 1, "17": 2, "18": 3, "19": 2, "2": 3,
           "20": 1, "21": 3, "3": 3, "4": 1, "5": 3, "6": 3, "7": 3, "8": 1, "9": 3},
      "22":
          {"1": 2, "10": 2, "11": 3, "12": 2, "13": 3, "14": 1, "15": 3, "16": 3, "17": 2, "18": 1, "19": 1, "2": 2,
           "20": 3, "21": 3, "3": 1, "4": 1, "5": 1, "6": 3, "7": 3, "8": 2, "9": 3},
      "23":
          {"1": 1, "10": 1, "11": 3, "12": 2, "13": 2, "14": 2, "15": 2, "16": 3, "17": 2, "18": 3, "19": 1, "2": 2,
           "20": 1, "21": 2, "3": 1, "4": 2, "5": 1, "6": 1, "7": 3, "8": 3, "9": 2},
      "24":
          {"1": 2, "10": 1, "11": 2, "12": 1, "13": 3, "14": 2, "15": 3, "16": 2, "17": 2, "18": 2, "19": 2, "2": 3,
           "20": 3, "21": 3, "3": 1, "4": 2, "5": 1, "6": 3, "7": 3, "8": 2, "9": 2},
      "25":
          {"1": 3, "10": 2, "11": 2, "12": 1, "13": 1, "14": 1, "15": 1, "16": 3, "17": 1, "18": 3, "19": 2, "2": 1,
           "20": 3, "21": 2, "3": 3, "4": 1, "5": 2, "6": 2, "7": 2, "8": 1, "9": 1},
      "26":
          {"1": 1, "10": 3, "11": 2, "12": 2, "13": 3, "14": 2, "15": 1, "16": 2, "17": 2, "18": 1, "19": 3, "2": 3,
           "20": 3, "21": 3, "3": 3, "4": 1, "5": 1, "6": 1, "7": 2, "8": 3, "9": 1},
      "27":
          {"1": 1, "10": 1, "11": 1, "12": 3, "13": 1, "14": 2, "15": 2, "16": 2, "17": 2, "18": 3, "19": 1, "2": 2,
           "20": 1, "21": 3, "3": 1, "4": 3, "5": 2, "6": 2, "7": 1, "8": 2, "9": 1},
      "28":
          {"1": 3, "10": 1, "11": 2, "12": 1, "13": 2, "14": 3, "15": 1, "16": 3, "17": 1, "18": 3, "19": 1, "2": 3,
           "20": 1, "21": 3, "3": 2, "4": 2, "5": 2, "6": 3, "7": 2, "8": 3, "9": 3},
      "29":
          {"1": 2, "10": 2, "11": 3, "12": 3, "13": 1, "14": 1, "15": 2, "16": 3, "17": 2, "18": 1, "19": 1, "2": 2,
           "20": 2, "21": 2, "3": 1, "4": 1, "5": 2, "6": 3, "7": 3, "8": 2, "9": 1},
      "3":
          {"1": 3, "10": 2, "11": 3, "12": 3, "13": 3, "14": 2, "15": 1, "16": 1, "17": 1, "18": 2, "19": 2, "2": 2,
           "20": 2, "21": 1, "3": 2, "4": 1, "5": 3, "6": 1, "7": 2, "8": 2, "9": 2},
      "4":
          {"1": 3, "10": 2, "11": 3, "12": 2, "13": 1, "14": 2, "15": 1, "16": 3, "17": 3, "18": 3, "19": 3, "2": 2,
           "20": 3, "21": 3, "3": 3, "4": 1, "5": 2, "6": 2, "7": 3, "8": 1, "9": 1},
      "5":
          {"1": 1, "10": 2, "11": 2, "12": 3, "13": 2, "14": 2, "15": 2, "16": 2, "17": 3, "18": 3, "19": 3, "2": 1,
           "20": 2, "21": 2, "3": 3, "4": 2, "5": 1, "6": 3, "7": 2, "8": 2, "9": 3},
      "6":
          {"1": 1, "10": 3, "11": 2, "12": 2, "13": 1, "14": 2, "15": 1, "16": 3, "17": 3, "18": 3, "19": 2, "2": 1,
           "20": 2, "21": 2, "3": 1, "4": 3, "5": 2, "6": 2, "7": 3, "8": 2, "9": 1},
      "7":
          {"1": 3, "10": 2, "11": 3, "12": 1, "13": 1, "14": 2, "15": 1, "16": 2, "17": 1, "18": 3, "19": 1, "2": 2,
           "20": 2, "21": 2, "3": 3, "4": 3, "5": 1, "6": 2, "7": 3, "8": 1, "9": 3},
      "8":
          {"1": 1, "10": 1, "11": 3, "12": 3, "13": 1, "14": 1, "15": 3, "16": 1, "17": 2, "18": 1, "19": 3, "2": 3,
           "20": 3, "21": 3, "3": 2, "4": 3, "5": 2, "6": 1, "7": 3, "8": 3, "9": 1},
      "9":
          {"1": 3, "10": 2, "11": 3, "12": 2, "13": 1, "14": 1, "15": 2, "16": 3, "17": 3, "18": 3, "19": 3, "2": 3,
           "20": 2, "21": 2, "3": 2, "4": 2, "5": 1, "6": 1, "7": 1, "8": 3, "9": 3}},
 "demand_Function1D": {"1": 6, "2": 12, "3": 11, "4": 8, "5": 11, "6": 22}, "fin1": 609, "fin2": 3, "fin3": 126,
 "fin4": 3, "fin5": 29, "fin6": 44, "fin7": 6, "fin8": 22, "maxCost": 36, "n_customer": 6, "n_transshipment": 21,
 "n_warehouses": 29,
 "stock_Function1D":
     {"1": 44, "10": 44, "11": 44, "12": 44, "13": 44, "14": 44, "15": 44, "16": 44, "17": 44, "18": 44, "19": 44,
      "2": 44, "20": 44, "21": 44, "22": 44, "23": 44, "24": 44, "25": 44, "26": 44, "27": 44, "28": 44, "29": 44,
      "3": 44, "4": 44, "5": 44, "6": 44, "7": 44, "8": 44, "9": 44}}