{"c_avg_deg_cons": 3.00275, "c_avg_dom_cons": 8.43341, "c_avg_domdeg_cons": 3.60543, "c_bounds_d": 0, "c_bounds_r": 0, "c_bounds_z": 0, "c_cv_deg_cons": 3.0157, "c_cv_dom_cons": 1.75476, "c_cv_domdeg_cons": 0, "c_domain": 0, "c_ent_deg_cons": 0.149875, "c_ent_dom_cons": 1.1908, "c_ent_domdeg_cons": 0.484858, "c_logprod_deg_cons": 34361, "c_logprod_dom_cons": 93254.5, "c_max_deg_cons": 176, "c_max_dom_cons": 1115.81, "c_max_domdeg_cons": 6.33985, "c_min_deg_cons": 2, "c_min_dom_cons": 2, "c_min_domdeg_cons": 1, "c_num_cons": 32053, "c_priority": 0, "c_ratio_cons": 1.00175, "c_sum_ari_cons": 95665, "c_sum_dom_cons": 270316, "c_sum_domdeg_cons": 115565, "d_array_cons": 403, "d_bool_cons": 0, "d_bool_vars": 31559, "d_float_cons": 0, "d_float_vars": 0, "d_int_cons": 31559, "d_int_vars": 438, "d_ratio_array_cons": 0.0125729, "d_ratio_bool_cons": 0, "d_ratio_bool_vars": 0.986311, "d_ratio_float_cons": 0, "d_ratio_float_vars": 0, "d_ratio_int_cons": 0.984588, "d_ratio_int_vars": 0.0136888, "d_ratio_set_cons": 0, "d_ratio_set_vars": 0, "d_set_cons": 0, "d_set_vars": 0, "gc_diff_globs": 0, "gc_global_cons": 0, "gc_ratio_diff": 0, "gc_ratio_globs": 0, "o_deg": 0, "o_deg_avg": 0, "o_deg_cons": 0, "o_deg_std": 0, "o_dom": 0, "o_dom_avg": 0, "o_dom_deg": 0, "o_dom_std": 0, "s_bool_search": 0, "s_first_fail": 0, "s_goal": 1, "s_indomain_max": 0, "s_indomain_min": 1, "s_input_order": 1, "s_int_search": 1, "s_labeled_vars": 438, "s_other_val": 0, "s_other_var": 0, "s_set_search": 0, "v_avg_deg_vars": 3.008, "v_avg_dom_vars": 2.96156, "v_avg_domdeg_vars": 0.999235, "v_cv_deg_vars": 2.95485, "v_cv_dom_vars": 2.86514, "v_cv_domdeg_vars": 0, "v_def_vars": 0, "v_ent_deg_vars": 0.140472, "v_ent_dom_vars": 0.129825, "v_ent_domdeg_vars": 0, "v_intro_vars": 31559, "v_logprod_deg_vars": 34231.8, "v_logprod_dom_vars": 34194.1, "v_max_deg_vars": 85, "v_max_dom_vars": 81, "v_max_domdeg_vars": 1, "v_min_deg_vars": 2, "v_min_dom_vars": 2, "v_min_domdeg_vars": 0.5, "v_num_aliases": 0, "v_num_consts": 0, "v_num_vars": 31997, "v_ratio_bounded": 0, "v_ratio_vars": 0.998253, "v_sum_deg_vars": 96247, "v_sum_dom_vars": 94761, "v_sum_domdeg_vars": 31972.5}
