{"c_avg_deg_cons": 4.09899, "c_avg_dom_cons": 6.57193, "c_avg_domdeg_cons": 2.23647, "c_bounds_d": 0, "c_bounds_r": 0, "c_bounds_z": 0, "c_cv_deg_cons": 1.69022, "c_cv_dom_cons": 1.03201, "c_cv_domdeg_cons": 0.632342, "c_domain": 0, "c_ent_deg_cons": 0.670203, "c_ent_dom_cons": 1.52764, "c_ent_domdeg_cons": 0.98529, "c_logprod_deg_cons": 65239.5, "c_logprod_dom_cons": 103729, "c_max_deg_cons": 113, "c_max_dom_cons": 113, "c_max_domdeg_cons": 3.88409, "c_min_deg_cons": 2, "c_min_dom_cons": 2, "c_min_domdeg_cons": 1, "c_num_cons": 45862, "c_priority": 0, "c_ratio_cons": 1.16292, "c_sum_ari_cons": 117924, "c_sum_dom_cons": 301402, "c_sum_domdeg_cons": 102569, "d_array_cons": 0, "d_bool_cons": 0, "d_bool_vars": 19662, "d_float_cons": 0, "d_float_vars": 0, "d_int_cons": 18855, "d_int_vars": 19775, "d_ratio_array_cons": 0, "d_ratio_bool_cons": 0, "d_ratio_bool_vars": 0.498567, "d_ratio_float_cons": 0, "d_ratio_float_vars": 0, "d_ratio_int_cons": 0.411125, "d_ratio_int_vars": 0.501433, "d_ratio_set_cons": 0.160154, "d_ratio_set_vars": 0, "d_set_cons": 7345, "d_set_vars": 0, "gc_diff_globs": 0, "gc_global_cons": 0, "gc_ratio_diff": 0, "gc_ratio_globs": 0, "o_deg": 0, "o_deg_avg": 0, "o_deg_cons": 0, "o_deg_std": 0, "o_dom": 0, "o_dom_avg": 0, "o_dom_deg": 0, "o_dom_std": 0, "s_bool_search": 0, "s_first_fail": 0, "s_goal": 1, "s_indomain_max": 0, "s_indomain_min": 1, "s_input_order": 1, "s_int_search": 1, "s_labeled_vars": 113, "s_other_val": 0, "s_other_var": 0, "s_set_search": 0, "v_avg_deg_vars": 4.76679, "v_avg_dom_vars": 2.30659, "v_avg_domdeg_vars": 0.845386, "v_cv_deg_vars": 2.17003, "v_cv_dom_vars": 2.45247, "v_cv_domdeg_vars": 0, "v_def_vars": 0, "v_ent_deg_vars": 1.07744, "v_ent_dom_vars": 0.0283315, "v_ent_domdeg_vars": 0.672043, "v_intro_vars": 39324, "v_logprod_deg_vars": 60196.1, "v_logprod_dom_vars": 40088.8, "v_max_deg_vars": 174, "v_max_dom_vars": 109, "v_max_domdeg_vars": 1, "v_min_deg_vars": 0, "v_min_dom_vars": 2, "v_min_domdeg_vars": 0.117647, "v_num_aliases": 0, "v_num_consts": 1201, "v_num_vars": 39437, "v_ratio_bounded": 0.0304536, "v_ratio_vars": 0.859906, "v_sum_deg_vars": 187988, "v_sum_dom_vars": 90965, "v_sum_domdeg_vars": 33339.5}
